{
"meta":{"test_sets":[],"test_metrics":[],"learn_metrics":[{"best_value":"Min","name":"Logloss"}],"launch_mode":"Train","parameters":"","iteration_count":1000,"learn_sets":["learn"],"name":"experiment"},
"iterations":[
{"learn":[0.6781999048],"iteration":0,"passed_time":0.005004060869,"remaining_time":4.999056808},
{"learn":[0.6598544361],"iteration":1,"passed_time":0.00947864271,"remaining_time":4.729842712},
{"learn":[0.6432211828],"iteration":2,"passed_time":0.01387777227,"remaining_time":4.612046316},
{"learn":[0.6276219525],"iteration":3,"passed_time":0.01852882294,"remaining_time":4.613676912},
{"learn":[0.6134792087],"iteration":4,"passed_time":0.02230684278,"remaining_time":4.439061712},
{"learn":[0.6000178532],"iteration":5,"passed_time":0.0266897984,"remaining_time":4.421609936},
{"learn":[0.5878957297],"iteration":6,"passed_time":0.03047373683,"remaining_time":4.322917239},
{"learn":[0.5712104078],"iteration":7,"passed_time":0.03511494381,"remaining_time":4.354253033},
{"learn":[0.5602311135],"iteration":8,"passed_time":0.03906033197,"remaining_time":4.300976553},
{"learn":[0.548612112],"iteration":9,"passed_time":0.04294140273,"remaining_time":4.25119887},
{"learn":[0.5392470451],"iteration":10,"passed_time":0.04694540839,"remaining_time":4.22081899},
{"learn":[0.5305740876],"iteration":11,"passed_time":0.05217983662,"remaining_time":4.296139882},
{"learn":[0.5205438276],"iteration":12,"passed_time":0.0560655317,"remaining_time":4.256667676},
{"learn":[0.5084202265],"iteration":13,"passed_time":0.06013224994,"remaining_time":4.23502846},
{"learn":[0.4975163015],"iteration":14,"passed_time":0.06410502112,"remaining_time":4.209563053},
{"learn":[0.4920033303],"iteration":15,"passed_time":0.06949758359,"remaining_time":4.274101391},
{"learn":[0.4834903151],"iteration":16,"passed_time":0.07384157299,"remaining_time":4.269780367},
{"learn":[0.4790706691],"iteration":17,"passed_time":0.07762460246,"remaining_time":4.234853312},
{"learn":[0.472893379],"iteration":18,"passed_time":0.08221038309,"remaining_time":4.244651885},
{"learn":[0.4689064996],"iteration":19,"passed_time":0.08629854755,"remaining_time":4.22862883},
{"learn":[0.4652675209],"iteration":20,"passed_time":0.09003426635,"remaining_time":4.19731175},
{"learn":[0.4618021249],"iteration":21,"passed_time":0.0941290363,"remaining_time":4.184463523},
{"learn":[0.4576809522],"iteration":22,"passed_time":0.09874256259,"remaining_time":4.194412333},
{"learn":[0.4500521456],"iteration":23,"passed_time":0.1028163822,"remaining_time":4.181199544},
{"learn":[0.4446472021],"iteration":24,"passed_time":0.1066932722,"remaining_time":4.161037617},
{"learn":[0.4418063306],"iteration":25,"passed_time":0.1107476386,"remaining_time":4.148776923},
{"learn":[0.4384848598],"iteration":26,"passed_time":0.1155341897,"remaining_time":4.163509873},
{"learn":[0.4343904061],"iteration":27,"passed_time":0.1194197383,"remaining_time":4.145570916},
{"learn":[0.4314664676],"iteration":28,"passed_time":0.1233194195,"remaining_time":4.129074357},
{"learn":[0.4281640083],"iteration":29,"passed_time":0.1272159255,"remaining_time":4.113314924},
{"learn":[0.4231983935],"iteration":30,"passed_time":0.1323982384,"remaining_time":4.138512678},
{"learn":[0.4194059685],"iteration":31,"passed_time":0.1362606705,"remaining_time":4.121885281},
{"learn":[0.4142324728],"iteration":32,"passed_time":0.1402383303,"remaining_time":4.109408042},
{"learn":[0.4119613364],"iteration":33,"passed_time":0.1440228551,"remaining_time":4.091943471},
{"learn":[0.4074364607],"iteration":34,"passed_time":0.1500589441,"remaining_time":4.137339458},
{"learn":[0.4051191619],"iteration":35,"passed_time":0.154637809,"remaining_time":4.140856884},
{"learn":[0.4018214403],"iteration":36,"passed_time":0.1586529363,"remaining_time":4.129264262},
{"learn":[0.3992239496],"iteration":37,"passed_time":0.1633230018,"remaining_time":4.13465073},
{"learn":[0.3955684494],"iteration":38,"passed_time":0.1682647768,"remaining_time":4.146216681},
{"learn":[0.3935470846],"iteration":39,"passed_time":0.1721290268,"remaining_time":4.131096644},
{"learn":[0.3911184979],"iteration":40,"passed_time":0.1759670156,"remaining_time":4.115911413},
{"learn":[0.387493654],"iteration":41,"passed_time":0.1811520676,"remaining_time":4.1319924},
{"learn":[0.3847164112],"iteration":42,"passed_time":0.185341676,"remaining_time":4.124929858},
{"learn":[0.3816663564],"iteration":43,"passed_time":0.1893441463,"remaining_time":4.113931905},
{"learn":[0.3802918883],"iteration":44,"passed_time":0.1931729905,"remaining_time":4.099560132},
{"learn":[0.3772129159],"iteration":45,"passed_time":0.1982095941,"remaining_time":4.110694626},
{"learn":[0.3759515929],"iteration":46,"passed_time":0.2020150429,"remaining_time":4.09617736},
{"learn":[0.3746317744],"iteration":47,"passed_time":0.2060696411,"remaining_time":4.087047882},
{"learn":[0.3712087213],"iteration":48,"passed_time":0.210657247,"remaining_time":4.088470242},
{"learn":[0.3695048692],"iteration":49,"passed_time":0.2145860274,"remaining_time":4.077134521},
{"learn":[0.3682675966],"iteration":50,"passed_time":0.2185403918,"remaining_time":4.066565329},
{"learn":[0.3672312914],"iteration":51,"passed_time":0.2224370064,"remaining_time":4.055197732},
{"learn":[0.3662070741],"iteration":52,"passed_time":0.2278533284,"remaining_time":4.071266075},
{"learn":[0.3652777044],"iteration":53,"passed_time":0.2347312678,"remaining_time":4.112144062},
{"learn":[0.3644433721],"iteration":54,"passed_time":0.2386776411,"remaining_time":4.100915833},
{"learn":[0.3625650187],"iteration":55,"passed_time":0.243632584,"remaining_time":4.106949273},
{"learn":[0.3610550349],"iteration":56,"passed_time":0.2510056843,"remaining_time":4.152602812},
{"learn":[0.3594063912],"iteration":57,"passed_time":0.2556478949,"remaining_time":4.152074431},
{"learn":[0.3584976061],"iteration":58,"passed_time":0.2635888283,"remaining_time":4.204018431},
{"learn":[0.3576734569],"iteration":59,"passed_time":0.2690120529,"remaining_time":4.214522162},
{"learn":[0.3561700077],"iteration":60,"passed_time":0.2730008319,"remaining_time":4.202422643},
{"learn":[0.3554467876],"iteration":61,"passed_time":0.2805125762,"remaining_time":4.243883815},
{"learn":[0.3547950284],"iteration":62,"passed_time":0.2853264899,"remaining_time":4.243665414},
{"learn":[0.3540668216],"iteration":63,"passed_time":0.2892608126,"remaining_time":4.230439385},
{"learn":[0.3528370184],"iteration":64,"passed_time":0.2964639712,"remaining_time":4.264520201},
{"learn":[0.3515857248],"iteration":65,"passed_time":0.3004094876,"remaining_time":4.251249416},
{"learn":[0.3494079832],"iteration":66,"passed_time":0.3042853043,"remaining_time":4.237286401},
{"learn":[0.3470738897],"iteration":67,"passed_time":0.3101456771,"remaining_time":4.250820163},
{"learn":[0.3463342293],"iteration":68,"passed_time":0.3141975504,"remaining_time":4.239390137},
{"learn":[0.3454939072],"iteration":69,"passed_time":0.3181274392,"remaining_time":4.226550264},
{"learn":[0.3437014541],"iteration":70,"passed_time":0.3220321141,"remaining_time":4.213631465},
{"learn":[0.3429410698],"iteration":71,"passed_time":0.3273077031,"remaining_time":4.218632618},
{"learn":[0.3423434067],"iteration":72,"passed_time":0.331318286,"remaining_time":4.207288371},
{"learn":[0.341052986],"iteration":73,"passed_time":0.3351708671,"remaining_time":4.194165174},
{"learn":[0.3400706638],"iteration":74,"passed_time":0.3403473401,"remaining_time":4.197617194},
{"learn":[0.3387647522],"iteration":75,"passed_time":0.3445457778,"remaining_time":4.188951299},
{"learn":[0.3374613464],"iteration":76,"passed_time":0.3484556802,"remaining_time":4.176942764},
{"learn":[0.3367953024],"iteration":77,"passed_time":0.3523969733,"remaining_time":4.16551294},
{"learn":[0.3363605362],"iteration":78,"passed_time":0.3573921148,"remaining_time":4.166558705},
{"learn":[0.3347479574],"iteration":79,"passed_time":0.362177531,"remaining_time":4.165041606},
{"learn":[0.3343079748],"iteration":80,"passed_time":0.3661540685,"remaining_time":4.15426653},
{"learn":[0.333322754],"iteration":81,"passed_time":0.3700093386,"remaining_time":4.142299669},
{"learn":[0.3323255226],"iteration":82,"passed_time":0.3749062714,"remaining_time":4.142036758},
{"learn":[0.3319215605],"iteration":83,"passed_time":0.3788122165,"remaining_time":4.130857027},
{"learn":[0.3310854643],"iteration":84,"passed_time":0.3829611092,"remaining_time":4.122463705},
{"learn":[0.3305712596],"iteration":85,"passed_time":0.3869979769,"remaining_time":4.112978498},
{"learn":[0.3294359504],"iteration":86,"passed_time":0.3916968941,"remaining_time":4.110566256},
{"learn":[0.3290185177],"iteration":87,"passed_time":0.3955355935,"remaining_time":4.09918706},
{"learn":[0.3285849861],"iteration":88,"passed_time":0.3997616646,"remaining_time":4.091942433},
{"learn":[0.3281292743],"iteration":89,"passed_time":0.4056387186,"remaining_time":4.101458154},
{"learn":[0.327536626],"iteration":90,"passed_time":0.4103495135,"remaining_time":4.0989858},
{"learn":[0.3261505509],"iteration":91,"passed_time":0.4143112372,"remaining_time":4.089071776},
{"learn":[0.3257119025],"iteration":92,"passed_time":0.418444233,"remaining_time":4.080956122},
{"learn":[0.3253693628],"iteration":93,"passed_time":0.4248419463,"remaining_time":4.094753227},
{"learn":[0.324715477],"iteration":94,"passed_time":0.4299472853,"remaining_time":4.095813612},
{"learn":[0.324142643],"iteration":95,"passed_time":0.4352572089,"remaining_time":4.09867205},
{"learn":[0.3238260792],"iteration":96,"passed_time":0.4401916386,"remaining_time":4.097866492},
{"learn":[0.3234852527],"iteration":97,"passed_time":0.444205369,"remaining_time":4.088502478},
{"learn":[0.3231697574],"iteration":98,"passed_time":0.4480888009,"remaining_time":4.078060703},
{"learn":[0.3228972674],"iteration":99,"passed_time":0.4548449367,"remaining_time":4.09360443},
{"learn":[0.3219488218],"iteration":100,"passed_time":0.4592698411,"remaining_time":4.087956308},
{"learn":[0.321646864],"iteration":101,"passed_time":0.4632478622,"remaining_time":4.078397845},
{"learn":[0.3213290981],"iteration":102,"passed_time":0.4687573905,"remaining_time":4.082285236},
{"learn":[0.3211058109],"iteration":103,"passed_time":0.4726365132,"remaining_time":4.071945344},
{"learn":[0.3205372762],"iteration":104,"passed_time":0.476987334,"remaining_time":4.065749181},
{"learn":[0.320088192],"iteration":105,"passed_time":0.4808332928,"remaining_time":4.055329847},
{"learn":[0.3197849082],"iteration":106,"passed_time":0.4860166813,"remaining_time":4.056195293},
{"learn":[0.3190766221],"iteration":107,"passed_time":0.489843977,"remaining_time":4.045748403},
{"learn":[0.3188012186],"iteration":108,"passed_time":0.4936600634,"remaining_time":4.035331344},
{"learn":[0.3185041334],"iteration":109,"passed_time":0.4976278742,"remaining_time":4.026261891},
{"learn":[0.3182324033],"iteration":110,"passed_time":0.5018979114,"remaining_time":4.019704894},
{"learn":[0.3179609473],"iteration":111,"passed_time":0.5059605766,"remaining_time":4.011544571},
{"learn":[0.3176614043],"iteration":112,"passed_time":0.5097595164,"remaining_time":4.001386647},
{"learn":[0.3174235576],"iteration":113,"passed_time":0.5142511322,"remaining_time":3.996723711},
{"learn":[0.3171116719],"iteration":114,"passed_time":0.5182670033,"remaining_time":3.988402591},
{"learn":[0.3167716837],"iteration":115,"passed_time":0.5221969576,"remaining_time":3.979500953},
{"learn":[0.316432507],"iteration":116,"passed_time":0.5261265177,"remaining_time":3.970681326},
{"learn":[0.3161658613],"iteration":117,"passed_time":0.5320416132,"remaining_time":3.976785617},
{"learn":[0.3151214718],"iteration":118,"passed_time":0.5362318729,"remaining_time":3.969918319},
{"learn":[0.3148915563],"iteration":119,"passed_time":0.5408241467,"remaining_time":3.966043742},
{"learn":[0.3146684763],"iteration":120,"passed_time":0.5446698397,"remaining_time":3.956733794},
{"learn":[0.3143033446],"iteration":121,"passed_time":0.5501731885,"remaining_time":3.959443111},
{"learn":[0.3140958845],"iteration":122,"passed_time":0.5543964577,"remaining_time":3.952891817},
{"learn":[0.3138366957],"iteration":123,"passed_time":0.5582857156,"remaining_time":3.944018442},
{"learn":[0.3134464394],"iteration":124,"passed_time":0.5629532031,"remaining_time":3.940672422},
{"learn":[0.3131913076],"iteration":125,"passed_time":0.5669384998,"remaining_time":3.932573403},
{"learn":[0.3130103436],"iteration":126,"passed_time":0.5709106787,"remaining_time":3.924448996},
{"learn":[0.312812907],"iteration":127,"passed_time":0.5747861157,"remaining_time":3.915730413},
{"learn":[0.3126565142],"iteration":128,"passed_time":0.5794171748,"remaining_time":3.912188832},
{"learn":[0.3123656269],"iteration":129,"passed_time":0.5834948602,"remaining_time":3.904927142},
{"learn":[0.3121270607],"iteration":130,"passed_time":0.5874166429,"remaining_time":3.896679868},
{"learn":[0.3118446144],"iteration":131,"passed_time":0.5915424449,"remaining_time":3.889839713},
{"learn":[0.3115783413],"iteration":132,"passed_time":0.5964737484,"remaining_time":3.888291277},
{"learn":[0.3113043119],"iteration":133,"passed_time":0.6003614633,"remaining_time":3.879947964},
{"learn":[0.3110468105],"iteration":134,"passed_time":0.60464217,"remaining_time":3.874188719},
{"learn":[0.3107951456],"iteration":135,"passed_time":0.6085603992,"remaining_time":3.866148418},
{"learn":[0.3105703265],"iteration":136,"passed_time":0.6137024849,"remaining_time":3.865877697},
{"learn":[0.3100294982],"iteration":137,"passed_time":0.617656542,"remaining_time":3.858115502},
{"learn":[0.3097685745],"iteration":138,"passed_time":0.6216460794,"remaining_time":3.850627873},
{"learn":[0.3094104302],"iteration":139,"passed_time":0.6255470221,"remaining_time":3.842645993},
{"learn":[0.3092914102],"iteration":140,"passed_time":0.6319973181,"remaining_time":3.850253165},
{"learn":[0.3090694065],"iteration":141,"passed_time":0.6367767899,"remaining_time":3.847566801},
{"learn":[0.3088283819],"iteration":142,"passed_time":0.6406390934,"remaining_time":3.839354567},
{"learn":[0.3085509242],"iteration":143,"passed_time":0.6480942963,"remaining_time":3.852560539},
{"learn":[0.3084409614],"iteration":144,"passed_time":0.6525271268,"remaining_time":3.847659954},
{"learn":[0.3081943569],"iteration":145,"passed_time":0.6566642378,"remaining_time":3.841036021},
{"learn":[0.3080734463],"iteration":146,"passed_time":0.663159121,"remaining_time":3.848127416},
{"learn":[0.3077484299],"iteration":147,"passed_time":0.6675668263,"remaining_time":3.843019838},
{"learn":[0.3075929163],"iteration":148,"passed_time":0.6715031355,"remaining_time":3.835229317},
{"learn":[0.3074433098],"iteration":149,"passed_time":0.6770332325,"remaining_time":3.836521651},
{"learn":[0.3072086353],"iteration":150,"passed_time":0.6810116184,"remaining_time":3.8289991},
{"learn":[0.306923567],"iteration":151,"passed_time":0.6849010051,"remaining_time":3.82102666},
{"learn":[0.3067130574],"iteration":152,"passed_time":0.6888037452,"remaining_time":3.813181518},
{"learn":[0.3065963923],"iteration":153,"passed_time":0.6939527803,"remaining_time":3.812234105},
{"learn":[0.3064091447],"iteration":154,"passed_time":0.6979954047,"remaining_time":3.805200755},
{"learn":[0.3062665434],"iteration":155,"passed_time":0.7018981961,"remaining_time":3.797449215},
{"learn":[0.3058465527],"iteration":156,"passed_time":0.705846326,"remaining_time":3.789990145},
{"learn":[0.30564966],"iteration":157,"passed_time":0.7103055193,"remaining_time":3.785299033},
{"learn":[0.3054994647],"iteration":158,"passed_time":0.714189014,"remaining_time":3.777565791},
{"learn":[0.3052343677],"iteration":159,"passed_time":0.7180801676,"remaining_time":3.76992088},
{"learn":[0.3050333166],"iteration":160,"passed_time":0.7222007278,"remaining_time":3.763518078},
{"learn":[0.3049087177],"iteration":161,"passed_time":0.7265434383,"remaining_time":3.758292601},
{"learn":[0.304767024],"iteration":162,"passed_time":0.7304821067,"remaining_time":3.751003211},
{"learn":[0.3045735644],"iteration":163,"passed_time":0.7350219883,"remaining_time":3.746819404},
{"learn":[0.3044332654],"iteration":164,"passed_time":0.7401545736,"remaining_time":3.745630721},
{"learn":[0.3042494458],"iteration":165,"passed_time":0.7440510841,"remaining_time":3.738184362},
{"learn":[0.3041050192],"iteration":166,"passed_time":0.7478227138,"remaining_time":3.730157608},
{"learn":[0.3039330399],"iteration":167,"passed_time":0.751706431,"remaining_time":3.722736611},
{"learn":[0.3032140327],"iteration":168,"passed_time":0.7578139786,"remaining_time":3.726292404},
{"learn":[0.3029529315],"iteration":169,"passed_time":0.762231664,"remaining_time":3.721484006},
{"learn":[0.3025677145],"iteration":170,"passed_time":0.7661512395,"remaining_time":3.714265366},
{"learn":[0.3024201535],"iteration":171,"passed_time":0.770575767,"remaining_time":3.709515901},
{"learn":[0.3022648453],"iteration":172,"passed_time":0.774709597,"remaining_time":3.703380559},
{"learn":[0.3016493743],"iteration":173,"passed_time":0.7784442248,"remaining_time":3.695373159},
{"learn":[0.301071625],"iteration":174,"passed_time":0.7830144366,"remaining_time":3.691353773},
{"learn":[0.300916113],"iteration":175,"passed_time":0.789320408,"remaining_time":3.695454638},
{"learn":[0.3007860245],"iteration":176,"passed_time":0.7932940997,"remaining_time":3.688593469},
{"learn":[0.3006280471],"iteration":177,"passed_time":0.7971660733,"remaining_time":3.681295013},
{"learn":[0.299895125],"iteration":178,"passed_time":0.8014408894,"remaining_time":3.675882515},
{"learn":[0.2996734893],"iteration":179,"passed_time":0.8057023329,"remaining_time":3.670421739},
{"learn":[0.2995360369],"iteration":180,"passed_time":0.8096172693,"remaining_time":3.663406318},
{"learn":[0.2994333715],"iteration":181,"passed_time":0.8135335237,"remaining_time":3.656430892},
{"learn":[0.2992669853],"iteration":182,"passed_time":0.8178877289,"remaining_time":3.651444123},
{"learn":[0.2989424041],"iteration":183,"passed_time":0.8234771298,"remaining_time":3.651942054},
{"learn":[0.298755443],"iteration":184,"passed_time":0.8277162898,"remaining_time":3.646425817},
{"learn":[0.2986001828],"iteration":185,"passed_time":0.8317664309,"remaining_time":3.640096101},
{"learn":[0.2984976442],"iteration":186,"passed_time":0.8385523473,"remaining_time":3.645684804},
{"learn":[0.2983090573],"iteration":187,"passed_time":0.8437373448,"remaining_time":3.644227255},
{"learn":[0.2981365776],"iteration":188,"passed_time":0.847870109,"remaining_time":3.638215124},
{"learn":[0.297821833],"iteration":189,"passed_time":0.8548934748,"remaining_time":3.644545866},
{"learn":[0.2976894999],"iteration":190,"passed_time":0.8607521258,"remaining_time":3.645803507},
{"learn":[0.2975158709],"iteration":191,"passed_time":0.8646767401,"remaining_time":3.638847948},
{"learn":[0.2973117175],"iteration":192,"passed_time":0.8720607106,"remaining_time":3.646388567},
{"learn":[0.2971911487],"iteration":193,"passed_time":0.8777322986,"remaining_time":3.646660993},
{"learn":[0.2970307379],"iteration":194,"passed_time":0.8834243981,"remaining_time":3.646957131},
{"learn":[0.2968276647],"iteration":195,"passed_time":0.8888237254,"remaining_time":3.6459912},
{"learn":[0.2966743317],"iteration":196,"passed_time":0.8941107557,"remaining_time":3.644522522},
{"learn":[0.2965015938],"iteration":197,"passed_time":0.8996565931,"remaining_time":3.644063574},
{"learn":[0.2963783357],"iteration":198,"passed_time":0.9049367449,"remaining_time":3.642484084},
{"learn":[0.2962633257],"iteration":199,"passed_time":0.9092275694,"remaining_time":3.636910278},
{"learn":[0.2961548287],"iteration":200,"passed_time":0.9131399001,"remaining_time":3.629844678},
{"learn":[0.2956504565],"iteration":201,"passed_time":0.9202258884,"remaining_time":3.635347816},
{"learn":[0.2954742219],"iteration":202,"passed_time":0.9253603339,"remaining_time":3.633064956},
{"learn":[0.2953224424],"iteration":203,"passed_time":0.9292381119,"remaining_time":3.625850672},
{"learn":[0.2952544488],"iteration":204,"passed_time":0.9364090038,"remaining_time":3.631439795},
{"learn":[0.2951339853],"iteration":205,"passed_time":0.9404996282,"remaining_time":3.625032548},
{"learn":[0.295042244],"iteration":206,"passed_time":0.9444419921,"remaining_time":3.618079709},
{"learn":[0.294931402],"iteration":207,"passed_time":0.9508785963,"remaining_time":3.620653117},
{"learn":[0.2943906883],"iteration":208,"passed_time":0.9555988659,"remaining_time":3.616644512},
{"learn":[0.2942769745],"iteration":209,"passed_time":0.9595018483,"remaining_time":3.609554572},
{"learn":[0.2941410277],"iteration":210,"passed_time":0.9654678884,"remaining_time":3.610209308},
{"learn":[0.2939962332],"iteration":211,"passed_time":0.9700914401,"remaining_time":3.605811579},
{"learn":[0.2937157059],"iteration":212,"passed_time":0.9745827834,"remaining_time":3.600923242},
{"learn":[0.2935966486],"iteration":213,"passed_time":0.979293976,"remaining_time":3.596846099},
{"learn":[0.2934501767],"iteration":214,"passed_time":0.9832595055,"remaining_time":3.59004052},
{"learn":[0.293306054],"iteration":215,"passed_time":0.9871859693,"remaining_time":3.583119444},
{"learn":[0.2931184681],"iteration":216,"passed_time":0.9910057161,"remaining_time":3.575840902},
{"learn":[0.2929734851],"iteration":217,"passed_time":0.9954884856,"remaining_time":3.570972457},
{"learn":[0.2928070177],"iteration":218,"passed_time":0.9995937567,"remaining_time":3.564761297},
{"learn":[0.2927149155],"iteration":219,"passed_time":1.004288869,"remaining_time":3.560660534},
{"learn":[0.2922918911],"iteration":220,"passed_time":1.008202485,"remaining_time":3.553799711},
{"learn":[0.2921735673],"iteration":221,"passed_time":1.012996365,"remaining_time":3.550050325},
{"learn":[0.2918210134],"iteration":222,"passed_time":1.016809002,"remaining_time":3.542872622},
{"learn":[0.2916518971],"iteration":223,"passed_time":1.021984251,"remaining_time":3.54044544},
{"learn":[0.2914934495],"iteration":224,"passed_time":1.02818086,"remaining_time":3.541511852},
{"learn":[0.2912906614],"iteration":225,"passed_time":1.032552817,"remaining_time":3.536264958},
{"learn":[0.2910919062],"iteration":226,"passed_time":1.036478311,"remaining_time":3.529505437},
{"learn":[0.2909603626],"iteration":227,"passed_time":1.040492428,"remaining_time":3.523070853},
{"learn":[0.2908788101],"iteration":228,"passed_time":1.045998035,"remaining_time":3.521678972},
{"learn":[0.2907485849],"iteration":229,"passed_time":1.049804019,"remaining_time":3.51456128},
{"learn":[0.29057196],"iteration":230,"passed_time":1.053761665,"remaining_time":3.507977144},
{"learn":[0.2904210846],"iteration":231,"passed_time":1.057643674,"remaining_time":3.501165266},
{"learn":[0.2902344169],"iteration":232,"passed_time":1.06352574,"remaining_time":3.500962416},
{"learn":[0.2900687296],"iteration":233,"passed_time":1.067481257,"remaining_time":3.494404456},
{"learn":[0.2898831],"iteration":234,"passed_time":1.071479579,"remaining_time":3.488007991},
{"learn":[0.2897706873],"iteration":235,"passed_time":1.076057644,"remaining_time":3.483508645},
{"learn":[0.2896960096],"iteration":236,"passed_time":1.080260882,"remaining_time":3.477801911},
{"learn":[0.2895781263],"iteration":237,"passed_time":1.084095539,"remaining_time":3.470927736},
{"learn":[0.2893960129],"iteration":238,"passed_time":1.088042148,"remaining_time":3.46443546},
{"learn":[0.2891932651],"iteration":239,"passed_time":1.093154862,"remaining_time":3.461657062},
{"learn":[0.2890050773],"iteration":240,"passed_time":1.097160312,"remaining_time":3.455372103},
{"learn":[0.2888817104],"iteration":241,"passed_time":1.101065324,"remaining_time":3.448791386},
{"learn":[0.2887601788],"iteration":242,"passed_time":1.105342738,"remaining_time":3.44339281},
{"learn":[0.2885719857],"iteration":243,"passed_time":1.11036936,"remaining_time":3.440324739},
{"learn":[0.2884348892],"iteration":244,"passed_time":1.114204575,"remaining_time":3.433569201},
{"learn":[0.2882752096],"iteration":245,"passed_time":1.118115478,"remaining_time":3.427069393},
{"learn":[0.2881680312],"iteration":246,"passed_time":1.121771077,"remaining_time":3.419812231},
{"learn":[0.2880188492],"iteration":247,"passed_time":1.127043093,"remaining_time":3.417485508},
{"learn":[0.2879072947],"iteration":248,"passed_time":1.131201133,"remaining_time":3.411775304},
{"learn":[0.2877820222],"iteration":249,"passed_time":1.134962472,"remaining_time":3.404887416},
{"learn":[0.2876657668],"iteration":250,"passed_time":1.139395251,"remaining_time":3.400028061},
{"learn":[0.2875038427],"iteration":251,"passed_time":1.143332493,"remaining_time":3.39370121},
{"learn":[0.2874177035],"iteration":252,"passed_time":1.147425584,"remaining_time":3.387853404},
{"learn":[0.2873140665],"iteration":253,"passed_time":1.151171279,"remaining_time":3.380999112},
{"learn":[0.2872185958],"iteration":254,"passed_time":1.155562232,"remaining_time":3.376054363},
{"learn":[0.2870953215],"iteration":255,"passed_time":1.160244233,"remaining_time":3.371959803},
{"learn":[0.2866560985],"iteration":256,"passed_time":1.164087381,"remaining_time":3.365435503},
{"learn":[0.2863991346],"iteration":257,"passed_time":1.168354174,"remaining_time":3.360150378},
{"learn":[0.2862705455],"iteration":258,"passed_time":1.173804913,"remaining_time":3.358260389},
{"learn":[0.2861584007],"iteration":259,"passed_time":1.182611896,"remaining_time":3.365895397},
{"learn":[0.286013385],"iteration":260,"passed_time":1.186499643,"remaining_time":3.359476001},
{"learn":[0.2859072533],"iteration":261,"passed_time":1.193044788,"remaining_time":3.360561272},
{"learn":[0.2857140097],"iteration":262,"passed_time":1.198580358,"remaining_time":3.358759405},
{"learn":[0.2855536249],"iteration":263,"passed_time":1.202539004,"remaining_time":3.352532982},
{"learn":[0.2854587092],"iteration":264,"passed_time":1.209547583,"remaining_time":3.35478292},
{"learn":[0.2853825136],"iteration":265,"passed_time":1.215519467,"remaining_time":3.35410259},
{"learn":[0.2852209422],"iteration":266,"passed_time":1.221940914,"remaining_time":3.354616815},
{"learn":[0.2851089476],"iteration":267,"passed_time":1.226775899,"remaining_time":3.350746113},
{"learn":[0.2849714665],"iteration":268,"passed_time":1.232046693,"remaining_time":3.348052538},
{"learn":[0.2848857656],"iteration":269,"passed_time":1.238853764,"remaining_time":3.349493511},
{"learn":[0.2847502068],"iteration":270,"passed_time":1.243814516,"remaining_time":3.345906947},
{"learn":[0.2845248666],"iteration":271,"passed_time":1.248265847,"remaining_time":3.340946826},
{"learn":[0.2843978486],"iteration":272,"passed_time":1.254002027,"remaining_time":3.339411992},
{"learn":[0.2841822605],"iteration":273,"passed_time":1.258667622,"remaining_time":3.335009831},
{"learn":[0.2840925039],"iteration":274,"passed_time":1.264575575,"remaining_time":3.333881063},
{"learn":[0.2838886471],"iteration":275,"passed_time":1.270848268,"remaining_time":3.333674441},
{"learn":[0.2837578149],"iteration":276,"passed_time":1.277539214,"remaining_time":3.33451571},
{"learn":[0.2836278229],"iteration":277,"passed_time":1.288901697,"remaining_time":3.347435342},
{"learn":[0.2835204661],"iteration":278,"passed_time":1.295564192,"remaining_time":3.348035062},
{"learn":[0.2833269609],"iteration":279,"passed_time":1.302151024,"remaining_time":3.348388348},
{"learn":[0.2831536694],"iteration":280,"passed_time":1.306828641,"remaining_time":3.343807092},
{"learn":[0.2830484936],"iteration":281,"passed_time":1.310761525,"remaining_time":3.337328989},
{"learn":[0.2829199272],"iteration":282,"passed_time":1.314618606,"remaining_time":3.330676822},
{"learn":[0.2828263687],"iteration":283,"passed_time":1.321772796,"remaining_time":3.332356767},
{"learn":[0.2826511055],"iteration":284,"passed_time":1.325552976,"remaining_time":3.325510097},
{"learn":[0.2825439259],"iteration":285,"passed_time":1.329404824,"remaining_time":3.318863793},
{"learn":[0.2824332071],"iteration":286,"passed_time":1.335059988,"remaining_time":3.316716974},
{"learn":[0.2823261112],"iteration":287,"passed_time":1.339011418,"remaining_time":3.310333783},
{"learn":[0.2822280205],"iteration":288,"passed_time":1.342831481,"remaining_time":3.303644233},
{"learn":[0.2819247579],"iteration":289,"passed_time":1.346620198,"remaining_time":3.296897727},
{"learn":[0.2817561685],"iteration":290,"passed_time":1.352243514,"remaining_time":3.294641414},
{"learn":[0.2815758935],"iteration":291,"passed_time":1.356047846,"remaining_time":3.287951627},
{"learn":[0.2814437707],"iteration":292,"passed_time":1.359989373,"remaining_time":3.281612583},
{"learn":[0.281102157],"iteration":293,"passed_time":1.363770757,"remaining_time":3.274905287},
{"learn":[0.2810148033],"iteration":294,"passed_time":1.368559628,"remaining_time":3.270625552},
{"learn":[0.2809138733],"iteration":295,"passed_time":1.372369703,"remaining_time":3.264014429},
{"learn":[0.2808140625],"iteration":296,"passed_time":1.376388725,"remaining_time":3.257916746},
{"learn":[0.280673482],"iteration":297,"passed_time":1.381060691,"remaining_time":3.253371158},
{"learn":[0.2805544893],"iteration":298,"passed_time":1.385017196,"remaining_time":3.247147339},
{"learn":[0.280417981],"iteration":299,"passed_time":1.38958911,"remaining_time":3.24237459},
{"learn":[0.280251906],"iteration":300,"passed_time":1.394465863,"remaining_time":3.238311091},
{"learn":[0.2801029849],"iteration":301,"passed_time":1.399721846,"remaining_time":3.235118705},
{"learn":[0.2799791769],"iteration":302,"passed_time":1.404236815,"remaining_time":3.23020812},
{"learn":[0.2798956212],"iteration":303,"passed_time":1.408220401,"remaining_time":3.22408355},
{"learn":[0.2797594877],"iteration":304,"passed_time":1.414771079,"remaining_time":3.223822622},
{"learn":[0.2796282117],"iteration":305,"passed_time":1.420572829,"remaining_time":3.221822037},
{"learn":[0.2794685315],"iteration":306,"passed_time":1.424538945,"remaining_time":3.215653059},
{"learn":[0.2793991209],"iteration":307,"passed_time":1.429405756,"remaining_time":3.211522024},
{"learn":[0.2792671733],"iteration":308,"passed_time":1.433406812,"remaining_time":3.205450186},
{"learn":[0.2791187736],"iteration":309,"passed_time":1.437342268,"remaining_time":3.199245693},
{"learn":[0.2790533437],"iteration":310,"passed_time":1.441500076,"remaining_time":3.1935484},
{"learn":[0.2788985627],"iteration":311,"passed_time":1.447222922,"remaining_time":3.191312085},
{"learn":[0.2787130655],"iteration":312,"passed_time":1.45105764,"remaining_time":3.184909262},
{"learn":[0.278642285],"iteration":313,"passed_time":1.455008754,"remaining_time":3.178777088},
{"learn":[0.278559135],"iteration":314,"passed_time":1.459040007,"remaining_time":3.172833031},
{"learn":[0.2783597887],"iteration":315,"passed_time":1.46446754,"remaining_time":3.169923409},
{"learn":[0.2782241804],"iteration":316,"passed_time":1.468268264,"remaining_time":3.163492821},
{"learn":[0.2781635459],"iteration":317,"passed_time":1.472055305,"remaining_time":3.157049428},
{"learn":[0.2780896432],"iteration":318,"passed_time":1.476409662,"remaining_time":3.151833792},
{"learn":[0.277991923],"iteration":319,"passed_time":1.480453086,"remaining_time":3.145962807},
{"learn":[0.2779168656],"iteration":320,"passed_time":1.48430069,"remaining_time":3.139688999},
{"learn":[0.2778262166],"iteration":321,"passed_time":1.488099517,"remaining_time":3.133327554},
{"learn":[0.2777095297],"iteration":322,"passed_time":1.492362634,"remaining_time":3.127955117},
{"learn":[0.2775634838],"iteration":323,"passed_time":1.496411555,"remaining_time":3.122142627},
{"learn":[0.2774663257],"iteration":324,"passed_time":1.500241261,"remaining_time":3.115885695},
{"learn":[0.2773579763],"iteration":325,"passed_time":1.504171756,"remaining_time":3.109852035},
{"learn":[0.2772245161],"iteration":326,"passed_time":1.509084952,"remaining_time":3.105853739},
{"learn":[0.2771596924],"iteration":327,"passed_time":1.514742032,"remaining_time":3.10337392},
{"learn":[0.2770193655],"iteration":328,"passed_time":1.518666667,"remaining_time":3.097341439},
{"learn":[0.2769526467],"iteration":329,"passed_time":1.522593508,"remaining_time":3.091326212},
{"learn":[0.2768042584],"iteration":330,"passed_time":1.527904401,"remaining_time":3.088120981},
{"learn":[0.2766899647],"iteration":331,"passed_time":1.532809657,"remaining_time":3.084086901},
{"learn":[0.2765821874],"iteration":332,"passed_time":1.536689003,"remaining_time":3.077992688},
{"learn":[0.2763809332],"iteration":333,"passed_time":1.541111619,"remaining_time":3.072995025},
{"learn":[0.2762430179],"iteration":334,"passed_time":1.544934357,"remaining_time":3.066809992},
{"learn":[0.2760504304],"iteration":335,"passed_time":1.548809252,"remaining_time":3.060742092},
{"learn":[0.2758818406],"iteration":336,"passed_time":1.553064559,"remaining_time":3.055435616},
{"learn":[0.2757081323],"iteration":337,"passed_time":1.557799805,"remaining_time":3.051075358},
{"learn":[0.275532829],"iteration":338,"passed_time":1.561873064,"remaining_time":3.045422111},
{"learn":[0.2754092573],"iteration":339,"passed_time":1.565654067,"remaining_time":3.039210835},
{"learn":[0.2753101069],"iteration":340,"passed_time":1.569726089,"remaining_time":3.033576225},
{"learn":[0.2752098512],"iteration":341,"passed_time":1.576406106,"remaining_time":3.032968474},
{"learn":[0.2750539218],"iteration":342,"passed_time":1.580451523,"remaining_time":3.027278865},
{"learn":[0.2749039122],"iteration":343,"passed_time":1.584212167,"remaining_time":3.02105576},
{"learn":[0.2748180281],"iteration":344,"passed_time":1.589214851,"remaining_time":3.017205007},
{"learn":[0.2747101421],"iteration":345,"passed_time":1.59315433,"remaining_time":3.011337953},
{"learn":[0.2745810531],"iteration":346,"passed_time":1.596968471,"remaining_time":3.005246144},
{"learn":[0.2744624916],"iteration":347,"passed_time":1.600903562,"remaining_time":2.999394029},
{"learn":[0.2743147128],"iteration":348,"passed_time":1.605674892,"remaining_time":2.995112765},
{"learn":[0.2742068921],"iteration":349,"passed_time":1.611564148,"remaining_time":2.992904846},
{"learn":[0.2741203942],"iteration":350,"passed_time":1.616771518,"remaining_time":2.989415144},
{"learn":[0.2739358953],"iteration":351,"passed_time":1.621467461,"remaining_time":2.984974189},
{"learn":[0.2738669115],"iteration":352,"passed_time":1.626341301,"remaining_time":2.980857853},
{"learn":[0.2737388711],"iteration":353,"passed_time":1.630235455,"remaining_time":2.974949446},
{"learn":[0.2735805184],"iteration":354,"passed_time":1.634065519,"remaining_time":2.968935944},
{"learn":[0.273478386],"iteration":355,"passed_time":1.639344765,"remaining_time":2.96555626},
{"learn":[0.2732865122],"iteration":356,"passed_time":1.643263182,"remaining_time":2.959714919},
{"learn":[0.2731552674],"iteration":357,"passed_time":1.647089504,"remaining_time":2.953719166},
{"learn":[0.2730620825],"iteration":358,"passed_time":1.6508184,"remaining_time":2.947561545},
{"learn":[0.272971954],"iteration":359,"passed_time":1.655977961,"remaining_time":2.943960819},
{"learn":[0.2728122036],"iteration":360,"passed_time":1.659964668,"remaining_time":2.938275409},
{"learn":[0.2726979533],"iteration":361,"passed_time":1.663800823,"remaining_time":2.932334047},
{"learn":[0.2725910464],"iteration":362,"passed_time":1.667698303,"remaining_time":2.926511899},
{"learn":[0.2724457136],"iteration":363,"passed_time":1.672621756,"remaining_time":2.922492959},
{"learn":[0.2723272245],"iteration":364,"passed_time":1.676553435,"remaining_time":2.916743648},
{"learn":[0.2722191135],"iteration":365,"passed_time":1.680352151,"remaining_time":2.910773944},
{"learn":[0.2721386229],"iteration":366,"passed_time":1.684259095,"remaining_time":2.905002744},
{"learn":[0.272019905],"iteration":367,"passed_time":1.688570142,"remaining_time":2.899935679},
{"learn":[0.2719009453],"iteration":368,"passed_time":1.692534462,"remaining_time":2.894279798},
{"learn":[0.2717589244],"iteration":369,"passed_time":1.696480868,"remaining_time":2.88860256},
{"learn":[0.2716569687],"iteration":370,"passed_time":1.701229172,"remaining_time":2.884294202},
{"learn":[0.2714967306],"iteration":371,"passed_time":1.705233391,"remaining_time":2.878727338},
{"learn":[0.2713685231],"iteration":372,"passed_time":1.709148644,"remaining_time":2.873019303},
{"learn":[0.2712403216],"iteration":373,"passed_time":1.713161613,"remaining_time":2.867484412},
{"learn":[0.2710977718],"iteration":374,"passed_time":1.718070306,"remaining_time":2.863450509},
{"learn":[0.2709991466],"iteration":375,"passed_time":1.722837296,"remaining_time":2.859176789},
{"learn":[0.2709279233],"iteration":376,"passed_time":1.726667226,"remaining_time":2.853351942},
{"learn":[0.2707863114],"iteration":377,"passed_time":1.730443275,"remaining_time":2.847448987},
{"learn":[0.2706683139],"iteration":378,"passed_time":1.735505042,"remaining_time":2.843663935},
{"learn":[0.2704739323],"iteration":379,"passed_time":1.739608195,"remaining_time":2.838308108},
{"learn":[0.2703227367],"iteration":380,"passed_time":1.743403038,"remaining_time":2.832457954},
{"learn":[0.2702087445],"iteration":381,"passed_time":1.747305456,"remaining_time":2.826792596},
{"learn":[0.2701071997],"iteration":382,"passed_time":1.752040136,"remaining_time":2.82247719},
{"learn":[0.2700429189],"iteration":383,"passed_time":1.75591201,"remaining_time":2.816775515},
{"learn":[0.2699621784],"iteration":384,"passed_time":1.759654354,"remaining_time":2.810876435},
{"learn":[0.2698389241],"iteration":385,"passed_time":1.763434753,"remaining_time":2.805049064},
{"learn":[0.2697348458],"iteration":386,"passed_time":1.768156338,"remaining_time":2.800723089},
{"learn":[0.2696328088],"iteration":387,"passed_time":1.772172429,"remaining_time":2.795282285},
{"learn":[0.2694497085],"iteration":388,"passed_time":1.775921934,"remaining_time":2.789430081},
{"learn":[0.269258279],"iteration":389,"passed_time":1.779776047,"remaining_time":2.783752278},
{"learn":[0.2691141686],"iteration":390,"passed_time":1.784543738,"remaining_time":2.779506743},
{"learn":[0.2689739556],"iteration":391,"passed_time":1.788436926,"remaining_time":2.773902171},
{"learn":[0.268854094],"iteration":392,"passed_time":1.792736596,"remaining_time":2.768934132},
{"learn":[0.2686483665],"iteration":393,"passed_time":1.796836413,"remaining_time":2.763662097},
{"learn":[0.2684725533],"iteration":394,"passed_time":1.800693854,"remaining_time":2.758024764},
{"learn":[0.2684030927],"iteration":395,"passed_time":1.804498628,"remaining_time":2.75231609},
{"learn":[0.2682756044],"iteration":396,"passed_time":1.808258031,"remaining_time":2.746548093},
{"learn":[0.2681719867],"iteration":397,"passed_time":1.814278107,"remaining_time":2.744209598},
{"learn":[0.2680703852],"iteration":398,"passed_time":1.819730494,"remaining_time":2.74099756},
{"learn":[0.2679764043],"iteration":399,"passed_time":1.824199914,"remaining_time":2.736299871},
{"learn":[0.2678560776],"iteration":400,"passed_time":1.828048231,"remaining_time":2.730675537},
{"learn":[0.267671437],"iteration":401,"passed_time":1.833122431,"remaining_time":2.726883616},
{"learn":[0.2675330221],"iteration":402,"passed_time":1.837001383,"remaining_time":2.721314704},
{"learn":[0.267362877],"iteration":403,"passed_time":1.841114245,"remaining_time":2.716099233},
{"learn":[0.2672062951],"iteration":404,"passed_time":1.845676393,"remaining_time":2.711549269},
{"learn":[0.2670483636],"iteration":405,"passed_time":1.849786177,"remaining_time":2.706337411},
{"learn":[0.2669156239],"iteration":406,"passed_time":1.853648941,"remaining_time":2.700771061},
{"learn":[0.2667965856],"iteration":407,"passed_time":1.857580676,"remaining_time":2.695313137},
{"learn":[0.2666064868],"iteration":408,"passed_time":1.862057228,"remaining_time":2.690649932},
{"learn":[0.2664402187],"iteration":409,"passed_time":1.865901728,"remaining_time":2.685078096},
{"learn":[0.2663409984],"iteration":410,"passed_time":1.870321144,"remaining_time":2.680338573},
{"learn":[0.2662591764],"iteration":411,"passed_time":1.874145333,"remaining_time":2.674751106},
{"learn":[0.266117083],"iteration":412,"passed_time":1.878771637,"remaining_time":2.67031223},
{"learn":[0.2660295697],"iteration":413,"passed_time":1.882650987,"remaining_time":2.664815165},
{"learn":[0.2659213677],"iteration":414,"passed_time":1.886660811,"remaining_time":2.659509817},
{"learn":[0.2658451841],"iteration":415,"passed_time":1.890453587,"remaining_time":2.653905997},
{"learn":[0.2657336421],"iteration":416,"passed_time":1.895073195,"remaining_time":2.649466841},
{"learn":[0.2656712422],"iteration":417,"passed_time":1.89901133,"remaining_time":2.644077977},
{"learn":[0.2655503843],"iteration":418,"passed_time":1.902753472,"remaining_time":2.638424265},
{"learn":[0.265461849],"iteration":419,"passed_time":1.906839248,"remaining_time":2.6332542},
{"learn":[0.2653183913],"iteration":420,"passed_time":1.911901497,"remaining_time":2.629432225},
{"learn":[0.2652292132],"iteration":421,"passed_time":1.916447425,"remaining_time":2.624897184},
{"learn":[0.2651060575],"iteration":422,"passed_time":1.920248342,"remaining_time":2.619345847},
{"learn":[0.2649762031],"iteration":423,"passed_time":1.924039482,"remaining_time":2.613789485},
{"learn":[0.2648943736],"iteration":424,"passed_time":1.929736721,"remaining_time":2.61082027},
{"learn":[0.2647280359],"iteration":425,"passed_time":1.933930034,"remaining_time":2.605811829},
{"learn":[0.2646149645],"iteration":426,"passed_time":1.93786685,"remaining_time":2.600463009},
{"learn":[0.2644925401],"iteration":427,"passed_time":1.942205861,"remaining_time":2.5956583},
{"learn":[0.2643942852],"iteration":428,"passed_time":1.946172154,"remaining_time":2.590359674},
{"learn":[0.2643219368],"iteration":429,"passed_time":1.949963199,"remaining_time":2.584834938},
{"learn":[0.2641873712],"iteration":430,"passed_time":1.953854015,"remaining_time":2.579449964},
{"learn":[0.2640979575],"iteration":431,"passed_time":1.958434691,"remaining_time":2.574978946},
{"learn":[0.2640645722],"iteration":432,"passed_time":1.962367826,"remaining_time":2.569659486},
{"learn":[0.2640107523],"iteration":433,"passed_time":1.966268335,"remaining_time":2.564303865},
{"learn":[0.2638903287],"iteration":434,"passed_time":1.970083418,"remaining_time":2.558843979},
{"learn":[0.2637604868],"iteration":435,"passed_time":1.975561371,"remaining_time":2.555542692},
{"learn":[0.263666243],"iteration":436,"passed_time":1.980115406,"remaining_time":2.551041129},
{"learn":[0.2635900342],"iteration":437,"passed_time":1.984180312,"remaining_time":2.545911725},
{"learn":[0.2634745371],"iteration":438,"passed_time":1.988016579,"remaining_time":2.54049499},
{"learn":[0.263350506],"iteration":439,"passed_time":1.993052166,"remaining_time":2.536611848},
{"learn":[0.2632596129],"iteration":440,"passed_time":1.996845039,"remaining_time":2.531148246},
{"learn":[0.2631350371],"iteration":441,"passed_time":2.000608684,"remaining_time":2.525655307},
{"learn":[0.2630141222],"iteration":442,"passed_time":2.004952846,"remaining_time":2.520900079},
{"learn":[0.2629328382],"iteration":443,"passed_time":2.00977383,"remaining_time":2.516743805},
{"learn":[0.2628553882],"iteration":444,"passed_time":2.013807627,"remaining_time":2.511602771},
{"learn":[0.2627906195],"iteration":445,"passed_time":2.017690477,"remaining_time":2.506279202},
{"learn":[0.2626965997],"iteration":446,"passed_time":2.022333136,"remaining_time":2.501902067},
{"learn":[0.2626226427],"iteration":447,"passed_time":2.026252674,"remaining_time":2.496632759},
{"learn":[0.2625275554],"iteration":448,"passed_time":2.030425645,"remaining_time":2.491680469},
{"learn":[0.2624099069],"iteration":449,"passed_time":2.035275529,"remaining_time":2.48755898},
{"learn":[0.2622844747],"iteration":450,"passed_time":2.041081052,"remaining_time":2.484597555},
{"learn":[0.262199685],"iteration":451,"passed_time":2.044926948,"remaining_time":2.479247716},
{"learn":[0.2620445266],"iteration":452,"passed_time":2.048765141,"remaining_time":2.473895214},
{"learn":[0.2618866837],"iteration":453,"passed_time":2.053402359,"remaining_time":2.469510326},
{"learn":[0.2618101257],"iteration":454,"passed_time":2.057279807,"remaining_time":2.464214274},
{"learn":[0.2616901954],"iteration":455,"passed_time":2.06121942,"remaining_time":2.458998607},
{"learn":[0.2614824425],"iteration":456,"passed_time":2.064995085,"remaining_time":2.453593723},
{"learn":[0.2613499239],"iteration":457,"passed_time":2.069971016,"remaining_time":2.449616355},
{"learn":[0.261261632],"iteration":458,"passed_time":2.073675236,"remaining_time":2.444135735},
{"learn":[0.2611738191],"iteration":459,"passed_time":2.077508819,"remaining_time":2.438814701},
{"learn":[0.261088429],"iteration":460,"passed_time":2.081300419,"remaining_time":2.433451032},
{"learn":[0.261000869],"iteration":461,"passed_time":2.085637124,"remaining_time":2.428728945},
{"learn":[0.2608884125],"iteration":462,"passed_time":2.089657383,"remaining_time":2.423641501},
{"learn":[0.2607559567],"iteration":463,"passed_time":2.09343776,"remaining_time":2.41828155},
{"learn":[0.2606660667],"iteration":464,"passed_time":2.09734627,"remaining_time":2.413075816},
{"learn":[0.2605587396],"iteration":465,"passed_time":2.102165074,"remaining_time":2.408918776},
{"learn":[0.2603947509],"iteration":466,"passed_time":2.106077435,"remaining_time":2.403724353},
{"learn":[0.2601379136],"iteration":467,"passed_time":2.110683563,"remaining_time":2.39932405},
{"learn":[0.2600398796],"iteration":468,"passed_time":2.114503055,"remaining_time":2.394032243},
{"learn":[0.259939195],"iteration":469,"passed_time":2.119580672,"remaining_time":2.390165439},
{"learn":[0.2598287025],"iteration":470,"passed_time":2.124728521,"remaining_time":2.386372373},
{"learn":[0.2597494001],"iteration":471,"passed_time":2.128626237,"remaining_time":2.381175112},
{"learn":[0.2596407194],"iteration":472,"passed_time":2.13239919,"remaining_time":2.37584434},
{"learn":[0.2595618153],"iteration":473,"passed_time":2.137175085,"remaining_time":2.371633111},
{"learn":[0.2594783466],"iteration":474,"passed_time":2.140970798,"remaining_time":2.366336145},
{"learn":[0.2593775788],"iteration":475,"passed_time":2.144857146,"remaining_time":2.361145262},
{"learn":[0.2592623436],"iteration":476,"passed_time":2.148926192,"remaining_time":2.356160165},
{"learn":[0.2591621278],"iteration":477,"passed_time":2.152918774,"remaining_time":2.351095397},
{"learn":[0.2590983422],"iteration":478,"passed_time":2.156847089,"remaining_time":2.345965205},
{"learn":[0.2589478003],"iteration":479,"passed_time":2.160706791,"remaining_time":2.34076569},
{"learn":[0.2588200281],"iteration":480,"passed_time":2.165333938,"remaining_time":2.336399821},
{"learn":[0.2586900195],"iteration":481,"passed_time":2.169204537,"remaining_time":2.331219814},
{"learn":[0.2585679533],"iteration":482,"passed_time":2.173029241,"remaining_time":2.325996103},
{"learn":[0.258457032],"iteration":483,"passed_time":2.176918117,"remaining_time":2.320846588},
{"learn":[0.258323137],"iteration":484,"passed_time":2.181221803,"remaining_time":2.316142739},
{"learn":[0.2581848723],"iteration":485,"passed_time":2.185323972,"remaining_time":2.311227411},
{"learn":[0.2581068996],"iteration":486,"passed_time":2.189217885,"remaining_time":2.306096048},
{"learn":[0.2580168341],"iteration":487,"passed_time":2.192917508,"remaining_time":2.30076591},
{"learn":[0.257907122],"iteration":488,"passed_time":2.197852185,"remaining_time":2.29673306},
{"learn":[0.2577961053],"iteration":489,"passed_time":2.201787837,"remaining_time":2.291656728},
{"learn":[0.2576981958],"iteration":490,"passed_time":2.205590256,"remaining_time":2.286446925},
{"learn":[0.2575214075],"iteration":491,"passed_time":2.209514988,"remaining_time":2.281369134},
{"learn":[0.2574287691],"iteration":492,"passed_time":2.215476223,"remaining_time":2.278390356},
{"learn":[0.257324214],"iteration":493,"passed_time":2.221522887,"remaining_time":2.275487006},
{"learn":[0.2571817912],"iteration":494,"passed_time":2.225307747,"remaining_time":2.270263459},
{"learn":[0.2570724942],"iteration":495,"passed_time":2.230014459,"remaining_time":2.265982434},
{"learn":[0.256944783],"iteration":496,"passed_time":2.234781266,"remaining_time":2.261760517},
{"learn":[0.2567294897],"iteration":497,"passed_time":2.2386257,"remaining_time":2.256606629},
{"learn":[0.2566392531],"iteration":498,"passed_time":2.242392655,"remaining_time":2.251380201},
{"learn":[0.2565415358],"iteration":499,"passed_time":2.247549645,"remaining_time":2.247549645},
{"learn":[0.2563946916],"iteration":500,"passed_time":2.251638271,"remaining_time":2.242649695},
{"learn":[0.2563044709],"iteration":501,"passed_time":2.255621091,"remaining_time":2.237648015},
{"learn":[0.2562455715],"iteration":502,"passed_time":2.259446749,"remaining_time":2.232495098},
{"learn":[0.25609149],"iteration":503,"passed_time":2.264599483,"remaining_time":2.228653459},
{"learn":[0.2559972267],"iteration":504,"passed_time":2.268460558,"remaining_time":2.223540547},
{"learn":[0.255858939],"iteration":505,"passed_time":2.272256192,"remaining_time":2.218368694},
{"learn":[0.2557851286],"iteration":506,"passed_time":2.276075168,"remaining_time":2.213224966},
{"learn":[0.2556821352],"iteration":507,"passed_time":2.280979262,"remaining_time":2.209137396},
{"learn":[0.2556067956],"iteration":508,"passed_time":2.28476167,"remaining_time":2.203964597},
{"learn":[0.2555035671],"iteration":509,"passed_time":2.288610357,"remaining_time":2.198860931},
{"learn":[0.255425567],"iteration":510,"passed_time":2.29240896,"remaining_time":2.19371425},
{"learn":[0.2553108202],"iteration":511,"passed_time":2.297339891,"remaining_time":2.189652084},
{"learn":[0.2552058755],"iteration":512,"passed_time":2.301479716,"remaining_time":2.18483552},
{"learn":[0.2550986957],"iteration":513,"passed_time":2.305276173,"remaining_time":2.179696926},
{"learn":[0.2550161213],"iteration":514,"passed_time":2.30922788,"remaining_time":2.174709751},
{"learn":[0.2549285764],"iteration":515,"passed_time":2.314070671,"remaining_time":2.170562412},
{"learn":[0.2548260965],"iteration":516,"passed_time":2.318168696,"remaining_time":2.165716596},
{"learn":[0.2546456362],"iteration":517,"passed_time":2.321967692,"remaining_time":2.16059542},
{"learn":[0.2544792368],"iteration":518,"passed_time":2.32645013,"remaining_time":2.156112741},
{"learn":[0.2543847083],"iteration":519,"passed_time":2.330426386,"remaining_time":2.151162818},
{"learn":[0.254333242],"iteration":520,"passed_time":2.334167179,"remaining_time":2.146000151},
{"learn":[0.2542182207],"iteration":521,"passed_time":2.338292236,"remaining_time":2.141194806},
{"learn":[0.2541000345],"iteration":522,"passed_time":2.343632686,"remaining_time":2.137500557},
{"learn":[0.2539310783],"iteration":523,"passed_time":2.348104774,"remaining_time":2.133011207},
{"learn":[0.2537642054],"iteration":524,"passed_time":2.352085749,"remaining_time":2.128077582},
{"learn":[0.2536542815],"iteration":525,"passed_time":2.35594854,"remaining_time":2.12304108},
{"learn":[0.2535473135],"iteration":526,"passed_time":2.361142722,"remaining_time":2.119203999},
{"learn":[0.2534047512],"iteration":527,"passed_time":2.365838175,"remaining_time":2.114915945},
{"learn":[0.2532662244],"iteration":528,"passed_time":2.369996683,"remaining_time":2.110148276},
{"learn":[0.2532020529],"iteration":529,"passed_time":2.374791603,"remaining_time":2.105947271},
{"learn":[0.2530906353],"iteration":530,"passed_time":2.378831351,"remaining_time":2.101077032},
{"learn":[0.2529492088],"iteration":531,"passed_time":2.382578576,"remaining_time":2.095952582},
{"learn":[0.2527996004],"iteration":532,"passed_time":2.386505708,"remaining_time":2.09099093},
{"learn":[0.2526729817],"iteration":533,"passed_time":2.391754507,"remaining_time":2.087186517},
{"learn":[0.2525792268],"iteration":534,"passed_time":2.395705543,"remaining_time":2.082248743},
{"learn":[0.2524366113],"iteration":535,"passed_time":2.39947505,"remaining_time":2.077157506},
{"learn":[0.2523255102],"iteration":536,"passed_time":2.403354335,"remaining_time":2.072165842},
{"learn":[0.2521801129],"iteration":537,"passed_time":2.409051371,"remaining_time":2.068739282},
{"learn":[0.2519761595],"iteration":538,"passed_time":2.415073401,"remaining_time":2.06558226},
{"learn":[0.2519007866],"iteration":539,"passed_time":2.419309222,"remaining_time":2.060893041},
{"learn":[0.2517817183],"iteration":540,"passed_time":2.424777518,"remaining_time":2.057251166},
{"learn":[0.251626878],"iteration":541,"passed_time":2.428900633,"remaining_time":2.052465849},
{"learn":[0.2514893043],"iteration":542,"passed_time":2.432911613,"remaining_time":2.047588595},
{"learn":[0.2513717788],"iteration":543,"passed_time":2.436799181,"remaining_time":2.042611078},
{"learn":[0.2512952837],"iteration":544,"passed_time":2.441716366,"remaining_time":2.038497149},
{"learn":[0.2511669414],"iteration":545,"passed_time":2.445669108,"remaining_time":2.033578343},
{"learn":[0.2510605197],"iteration":546,"passed_time":2.449516524,"remaining_time":2.028575842},
{"learn":[0.2509500944],"iteration":547,"passed_time":2.454155725,"remaining_time":2.024230635},
{"learn":[0.2508273501],"iteration":548,"passed_time":2.458048778,"remaining_time":2.0192714},
{"learn":[0.2507525594],"iteration":549,"passed_time":2.461889641,"remaining_time":2.014273343},
{"learn":[0.250616121],"iteration":550,"passed_time":2.465769256,"remaining_time":2.009311064},
{"learn":[0.2505163135],"iteration":551,"passed_time":2.470206152,"remaining_time":2.004804993},
{"learn":[0.2504176285],"iteration":552,"passed_time":2.474338344,"remaining_time":2.000052875},
{"learn":[0.2503218074],"iteration":553,"passed_time":2.478150161,"remaining_time":1.995045076},
{"learn":[0.2501853277],"iteration":554,"passed_time":2.482101466,"remaining_time":1.990153428},
{"learn":[0.2500689372],"iteration":555,"passed_time":2.486487428,"remaining_time":1.985612262},
{"learn":[0.2499532488],"iteration":556,"passed_time":2.490745906,"remaining_time":1.980970263},
{"learn":[0.2498635429],"iteration":557,"passed_time":2.494726334,"remaining_time":1.97610939},
{"learn":[0.2497392021],"iteration":558,"passed_time":2.498576071,"remaining_time":1.971148564},
{"learn":[0.2496550289],"iteration":559,"passed_time":2.503349439,"remaining_time":1.966917416},
{"learn":[0.2495573979],"iteration":560,"passed_time":2.508268084,"remaining_time":1.962798019},
{"learn":[0.2494659697],"iteration":561,"passed_time":2.51231665,"remaining_time":1.957997674},
{"learn":[0.249338669],"iteration":562,"passed_time":2.516115023,"remaining_time":1.953005799},
{"learn":[0.2492046367],"iteration":563,"passed_time":2.520960586,"remaining_time":1.948827687},
{"learn":[0.2489872457],"iteration":564,"passed_time":2.525041975,"remaining_time":1.944058866},
{"learn":[0.2488604602],"iteration":565,"passed_time":2.529027405,"remaining_time":1.939218893},
{"learn":[0.2487079935],"iteration":566,"passed_time":2.53286463,"remaining_time":1.934268756},
{"learn":[0.2486811844],"iteration":567,"passed_time":2.537571069,"remaining_time":1.92998363},
{"learn":[0.2486145486],"iteration":568,"passed_time":2.541530325,"remaining_time":1.925131055},
{"learn":[0.2485652894],"iteration":569,"passed_time":2.545270582,"remaining_time":1.920116404},
{"learn":[0.2485029349],"iteration":570,"passed_time":2.549252634,"remaining_time":1.915287881},
{"learn":[0.2483657956],"iteration":571,"passed_time":2.553680488,"remaining_time":1.91079589},
{"learn":[0.2483028009],"iteration":572,"passed_time":2.557598896,"remaining_time":1.905924483},
{"learn":[0.2482202471],"iteration":573,"passed_time":2.561461187,"remaining_time":1.901014748},
{"learn":[0.2480428452],"iteration":574,"passed_time":2.565310516,"remaining_time":1.896099077},
{"learn":[0.2479625336],"iteration":575,"passed_time":2.569988928,"remaining_time":1.891797405},
{"learn":[0.2478737496],"iteration":576,"passed_time":2.573863324,"remaining_time":1.886905002},
{"learn":[0.2477453327],"iteration":577,"passed_time":2.577658246,"remaining_time":1.881958096},
{"learn":[0.247656262],"iteration":578,"passed_time":2.581436948,"remaining_time":1.877003377},
{"learn":[0.2475544999],"iteration":579,"passed_time":2.585879573,"remaining_time":1.872533484},
{"learn":[0.2473958747],"iteration":580,"passed_time":2.590205776,"remaining_time":1.867979725},
{"learn":[0.2473055173],"iteration":581,"passed_time":2.594052539,"remaining_time":1.863082408},
{"learn":[0.2471341659],"iteration":582,"passed_time":2.598546102,"remaining_time":1.858651329},
{"learn":[0.2470257831],"iteration":583,"passed_time":2.605623243,"remaining_time":1.856060393},
{"learn":[0.246926821],"iteration":584,"passed_time":2.610800309,"remaining_time":1.852106202},
{"learn":[0.2468474846],"iteration":585,"passed_time":2.615704675,"remaining_time":1.84795518},
{"learn":[0.2467953186],"iteration":586,"passed_time":2.620139177,"remaining_time":1.843471005},
{"learn":[0.2466922295],"iteration":587,"passed_time":2.623985373,"remaining_time":1.838574785},
{"learn":[0.246589714],"iteration":588,"passed_time":2.628036731,"remaining_time":1.833825291},
{"learn":[0.2464970064],"iteration":589,"passed_time":2.633335611,"remaining_time":1.829945085},
{"learn":[0.2464431092],"iteration":590,"passed_time":2.637144124,"remaining_time":1.825028674},
{"learn":[0.2463296186],"iteration":591,"passed_time":2.64090043,"remaining_time":1.820080026},
{"learn":[0.2462520977],"iteration":592,"passed_time":2.644694921,"remaining_time":1.815161607},
{"learn":[0.2460886812],"iteration":593,"passed_time":2.649783577,"remaining_time":1.811131536},
{"learn":[0.245993364],"iteration":594,"passed_time":2.653666461,"remaining_time":1.806277171},
{"learn":[0.2458551592],"iteration":595,"passed_time":2.657511012,"remaining_time":1.801400082},
{"learn":[0.2457475722],"iteration":596,"passed_time":2.661388381,"remaining_time":1.796548605},
{"learn":[0.2455961949],"iteration":597,"passed_time":2.666060229,"remaining_time":1.792234468},
{"learn":[0.2454974455],"iteration":598,"passed_time":2.669916023,"remaining_time":1.78737283},
{"learn":[0.2453758834],"iteration":599,"passed_time":2.673812385,"remaining_time":1.78254159},
{"learn":[0.2453159676],"iteration":600,"passed_time":2.677597023,"remaining_time":1.777639288},
{"learn":[0.2452312432],"iteration":601,"passed_time":2.682137644,"remaining_time":1.773240502},
{"learn":[0.2451125339],"iteration":602,"passed_time":2.686018878,"remaining_time":1.768407122},
{"learn":[0.2450376672],"iteration":603,"passed_time":2.689722602,"remaining_time":1.763460514},
{"learn":[0.2449609709],"iteration":604,"passed_time":2.693663444,"remaining_time":1.758672827},
{"learn":[0.2448672355],"iteration":605,"passed_time":2.698419452,"remaining_time":1.754417927},
{"learn":[0.2447749547],"iteration":606,"passed_time":2.70245177,"remaining_time":1.749692826},
{"learn":[0.2446323182],"iteration":607,"passed_time":2.706355999,"remaining_time":1.74488742},
{"learn":[0.2445448929],"iteration":608,"passed_time":2.710766569,"remaining_time":1.740410063},
{"learn":[0.2444671477],"iteration":609,"passed_time":2.715533586,"remaining_time":1.736160817},
{"learn":[0.2443285488],"iteration":610,"passed_time":2.71946764,"remaining_time":1.731379561},
{"learn":[0.2442488441],"iteration":611,"passed_time":2.723453574,"remaining_time":1.726633965},
{"learn":[0.2441250099],"iteration":612,"passed_time":2.728014996,"remaining_time":1.722254165},
{"learn":[0.244045284],"iteration":613,"passed_time":2.732152138,"remaining_time":1.717607044},
{"learn":[0.2439281442],"iteration":614,"passed_time":2.735968218,"remaining_time":1.712760592},
{"learn":[0.2438195516],"iteration":615,"passed_time":2.739871576,"remaining_time":1.707971891},
{"learn":[0.2437256399],"iteration":616,"passed_time":2.74475734,"remaining_time":1.703795885},
{"learn":[0.2436125698],"iteration":617,"passed_time":2.74873137,"remaining_time":1.699054018},
{"learn":[0.2434958087],"iteration":618,"passed_time":2.753453513,"remaining_time":1.694775103},
{"learn":[0.2433514618],"iteration":619,"passed_time":2.758464575,"remaining_time":1.690671837},
{"learn":[0.2432929198],"iteration":620,"passed_time":2.762595691,"remaining_time":1.68602861},
{"learn":[0.2431994279],"iteration":621,"passed_time":2.766643696,"remaining_time":1.681336523},
{"learn":[0.2430760293],"iteration":622,"passed_time":2.770681862,"remaining_time":1.676640549},
{"learn":[0.2430236781],"iteration":623,"passed_time":2.775163519,"remaining_time":1.672213915},
{"learn":[0.2429216564],"iteration":624,"passed_time":2.779173919,"remaining_time":1.667504351},
{"learn":[0.242851471],"iteration":625,"passed_time":2.782978582,"remaining_time":1.662674105},
{"learn":[0.2427589445],"iteration":626,"passed_time":2.786853009,"remaining_time":1.657888632},
{"learn":[0.2426611458],"iteration":627,"passed_time":2.7923932,"remaining_time":1.654092787},
{"learn":[0.2425748518],"iteration":628,"passed_time":2.796390789,"remaining_time":1.64938153},
{"learn":[0.2425069],"iteration":629,"passed_time":2.800192949,"remaining_time":1.644557764},
{"learn":[0.242422827],"iteration":630,"passed_time":2.803995416,"remaining_time":1.639737414},
{"learn":[0.2422842702],"iteration":631,"passed_time":2.810651176,"remaining_time":1.636581698},
{"learn":[0.2421847962],"iteration":632,"passed_time":2.81707955,"remaining_time":1.633283088},
{"learn":[0.2420957248],"iteration":633,"passed_time":2.821459784,"remaining_time":1.628792241},
{"learn":[0.2419783113],"iteration":634,"passed_time":2.827257289,"remaining_time":1.625116395},
{"learn":[0.2418693952],"iteration":635,"passed_time":2.831171767,"remaining_time":1.620356168},
{"learn":[0.2417610271],"iteration":636,"passed_time":2.835144826,"remaining_time":1.615631981},
{"learn":[0.241654051],"iteration":637,"passed_time":2.839974123,"remaining_time":1.611395976},
{"learn":[0.2415752894],"iteration":638,"passed_time":2.843890479,"remaining_time":1.606642352},
{"learn":[0.2414889833],"iteration":639,"passed_time":2.847930772,"remaining_time":1.601961059},
{"learn":[0.2413468115],"iteration":640,"passed_time":2.851783586,"remaining_time":1.597176767},
{"learn":[0.2412016353],"iteration":641,"passed_time":2.856486471,"remaining_time":1.592869403},
{"learn":[0.2410877373],"iteration":642,"passed_time":2.860376998,"remaining_time":1.58810978},
{"learn":[0.2409649525],"iteration":643,"passed_time":2.864149581,"remaining_time":1.583287657},
{"learn":[0.2408333816],"iteration":644,"passed_time":2.868145089,"remaining_time":1.578591483},
{"learn":[0.2407394144],"iteration":645,"passed_time":2.872995506,"remaining_time":1.574365958},
{"learn":[0.2406492807],"iteration":646,"passed_time":2.876955114,"remaining_time":1.569652481},
{"learn":[0.2405232365],"iteration":647,"passed_time":2.880936203,"remaining_time":1.564952999},
{"learn":[0.2403934691],"iteration":648,"passed_time":2.884857574,"remaining_time":1.560223434},
{"learn":[0.240249088],"iteration":649,"passed_time":2.890561545,"remaining_time":1.556456216},
{"learn":[0.2401344852],"iteration":650,"passed_time":2.895815854,"remaining_time":1.552441986},
{"learn":[0.2399932983],"iteration":651,"passed_time":2.899692947,"remaining_time":1.547688874},
{"learn":[0.2398909344],"iteration":652,"passed_time":2.904075875,"remaining_time":1.543207241},
{"learn":[0.2397775273],"iteration":653,"passed_time":2.908911184,"remaining_time":1.538965244},
{"learn":[0.2396345302],"iteration":654,"passed_time":2.912912707,"remaining_time":1.534282266},
{"learn":[0.2395228014],"iteration":655,"passed_time":2.916867381,"remaining_time":1.529576798},
{"learn":[0.2394042705],"iteration":656,"passed_time":2.921790372,"remaining_time":1.525379144},
{"learn":[0.2392500126],"iteration":657,"passed_time":2.925766535,"remaining_time":1.520687166},
{"learn":[0.2391854429],"iteration":658,"passed_time":2.929612313,"remaining_time":1.515929892},
{"learn":[0.2390917747],"iteration":659,"passed_time":2.933518341,"remaining_time":1.511206418},
{"learn":[0.2389934789],"iteration":660,"passed_time":2.93834799,"remaining_time":1.506959105},
{"learn":[0.2388795288],"iteration":661,"passed_time":2.94225558,"remaining_time":1.502239254},
{"learn":[0.2387322058],"iteration":662,"passed_time":2.946248273,"remaining_time":1.49756511},
{"learn":[0.2386459139],"iteration":663,"passed_time":2.950024785,"remaining_time":1.492783626},
{"learn":[0.2385456037],"iteration":664,"passed_time":2.955090237,"remaining_time":1.48865448},
{"learn":[0.2384548893],"iteration":665,"passed_time":2.959062974,"remaining_time":1.483974525},
{"learn":[0.2383415955],"iteration":666,"passed_time":2.962954757,"remaining_time":1.479256273},
{"learn":[0.2381746101],"iteration":667,"passed_time":2.966790443,"remaining_time":1.474512615},
{"learn":[0.2380805609],"iteration":668,"passed_time":2.971149941,"remaining_time":1.470030838},
{"learn":[0.2379675865],"iteration":669,"passed_time":2.975014435,"remaining_time":1.465305617},
{"learn":[0.237888643],"iteration":670,"passed_time":2.978838754,"remaining_time":1.460563264},
{"learn":[0.2377714664],"iteration":671,"passed_time":2.982985453,"remaining_time":1.455980995},
{"learn":[0.2376595108],"iteration":672,"passed_time":2.986997323,"remaining_time":1.451334509},
{"learn":[0.2375348361],"iteration":673,"passed_time":2.991763729,"remaining_time":1.44705486},
{"learn":[0.2374602173],"iteration":674,"passed_time":2.995782182,"remaining_time":1.442413643},
{"learn":[0.2373862743],"iteration":675,"passed_time":3.000582543,"remaining_time":1.43814903},
{"learn":[0.2372900675],"iteration":676,"passed_time":3.00573964,"remaining_time":1.434053033},
{"learn":[0.2371587492],"iteration":677,"passed_time":3.010530522,"remaining_time":1.429779983},
{"learn":[0.2370722437],"iteration":678,"passed_time":3.015189755,"remaining_time":1.425443168},
{"learn":[0.236984294],"iteration":679,"passed_time":3.020229482,"remaining_time":1.421284462},
{"learn":[0.2369297633],"iteration":680,"passed_time":3.024109753,"remaining_time":1.416580046},
{"learn":[0.2368478552],"iteration":681,"passed_time":3.027965798,"remaining_time":1.41186675},
{"learn":[0.2367518494],"iteration":682,"passed_time":3.033309204,"remaining_time":1.407846292},
{"learn":[0.2366245406],"iteration":683,"passed_time":3.037192633,"remaining_time":1.403147474},
{"learn":[0.2365238307],"iteration":684,"passed_time":3.041138073,"remaining_time":1.398479552},
{"learn":[0.2364424272],"iteration":685,"passed_time":3.04506885,"remaining_time":1.393807025},
{"learn":[0.2363258434],"iteration":686,"passed_time":3.050037682,"remaining_time":1.389609599},
{"learn":[0.2362409538],"iteration":687,"passed_time":3.053944513,"remaining_time":1.384928326},
{"learn":[0.2361166933],"iteration":688,"passed_time":3.057915914,"remaining_time":1.380278446},
{"learn":[0.2360357961],"iteration":689,"passed_time":3.061789819,"remaining_time":1.37558673},
{"learn":[0.235896406],"iteration":690,"passed_time":3.066795501,"remaining_time":1.371403488},
{"learn":[0.2357794856],"iteration":691,"passed_time":3.070626387,"remaining_time":1.366694981},
{"learn":[0.2356619018],"iteration":692,"passed_time":3.074447517,"remaining_time":1.361984687},
{"learn":[0.2355945051],"iteration":693,"passed_time":3.078412394,"remaining_time":1.357340335},
{"learn":[0.2355135985],"iteration":694,"passed_time":3.08251961,"remaining_time":1.352760404},
{"learn":[0.2353549679],"iteration":695,"passed_time":3.086632783,"remaining_time":1.348184434},
{"learn":[0.2352351414],"iteration":696,"passed_time":3.090515935,"remaining_time":1.343509797},
{"learn":[0.2351313286],"iteration":697,"passed_time":3.095356411,"remaining_time":1.339251628},
{"learn":[0.2350251871],"iteration":698,"passed_time":3.099186174,"remaining_time":1.334556564},
{"learn":[0.2349225887],"iteration":699,"passed_time":3.102954524,"remaining_time":1.329837653},
{"learn":[0.2348355088],"iteration":700,"passed_time":3.107280366,"remaining_time":1.325359243},
{"learn":[0.2347359609],"iteration":701,"passed_time":3.111947959,"remaining_time":1.321026342},
{"learn":[0.2346627761],"iteration":702,"passed_time":3.11673235,"remaining_time":1.316741832},
{"learn":[0.2345589132],"iteration":703,"passed_time":3.120666855,"remaining_time":1.312098564},
{"learn":[0.2344275262],"iteration":704,"passed_time":3.124602053,"remaining_time":1.307457597},
{"learn":[0.2343320798],"iteration":705,"passed_time":3.129528272,"remaining_time":1.30323132},
{"learn":[0.2342612256],"iteration":706,"passed_time":3.133452059,"remaining_time":1.298587628},
{"learn":[0.2342094375],"iteration":707,"passed_time":3.137224395,"remaining_time":1.293883507},
{"learn":[0.2341128937],"iteration":708,"passed_time":3.141014237,"remaining_time":1.2891892},
{"learn":[0.2340317205],"iteration":709,"passed_time":3.145671213,"remaining_time":1.284851622},
{"learn":[0.2339134515],"iteration":710,"passed_time":3.149620371,"remaining_time":1.280225439},
{"learn":[0.2337923369],"iteration":711,"passed_time":3.153886909,"remaining_time":1.275729536},
{"learn":[0.233688014],"iteration":712,"passed_time":3.159612882,"remaining_time":1.271821735},
{"learn":[0.2335815264],"iteration":713,"passed_time":3.163631602,"remaining_time":1.267224983},
{"learn":[0.2334458525],"iteration":714,"passed_time":3.16748497,"remaining_time":1.262563939},
{"learn":[0.233333094],"iteration":715,"passed_time":3.171223247,"remaining_time":1.2578595},
{"learn":[0.2332399798],"iteration":716,"passed_time":3.175765764,"remaining_time":1.25347519},
{"learn":[0.2330695518],"iteration":717,"passed_time":3.17964522,"remaining_time":1.248830017},
{"learn":[0.2329928313],"iteration":718,"passed_time":3.183675479,"remaining_time":1.24424591},
{"learn":[0.2328767798],"iteration":719,"passed_time":3.187499325,"remaining_time":1.239583071},
{"learn":[0.2328060836],"iteration":720,"passed_time":3.192803559,"remaining_time":1.235495413},
{"learn":[0.2327372249],"iteration":721,"passed_time":3.196625935,"remaining_time":1.230833809},
{"learn":[0.2326151382],"iteration":722,"passed_time":3.200501948,"remaining_time":1.226195076},
{"learn":[0.2325702542],"iteration":723,"passed_time":3.204203297,"remaining_time":1.221491865},
{"learn":[0.2324870587],"iteration":724,"passed_time":3.209074803,"remaining_time":1.21723527},
{"learn":[0.232386784],"iteration":725,"passed_time":3.214539294,"remaining_time":1.21320078},
{"learn":[0.2322689857],"iteration":726,"passed_time":3.219679753,"remaining_time":1.209040678},
{"learn":[0.2321574018],"iteration":727,"passed_time":3.22468835,"remaining_time":1.204828614},
{"learn":[0.2320123661],"iteration":728,"passed_time":3.229493638,"remaining_time":1.200538787},
{"learn":[0.2318971278],"iteration":729,"passed_time":3.233394518,"remaining_time":1.195913041},
{"learn":[0.2317970656],"iteration":730,"passed_time":3.237264971,"remaining_time":1.191278081},
{"learn":[0.2316595795],"iteration":731,"passed_time":3.242654518,"remaining_time":1.187201381},
{"learn":[0.2315429347],"iteration":732,"passed_time":3.246615722,"remaining_time":1.182600815},
{"learn":[0.231437472],"iteration":733,"passed_time":3.25063096,"remaining_time":1.178021574},
{"learn":[0.2313062551],"iteration":734,"passed_time":3.254472155,"remaining_time":1.173381117},
{"learn":[0.231207911],"iteration":735,"passed_time":3.259236864,"remaining_time":1.169074093},
{"learn":[0.2311340088],"iteration":736,"passed_time":3.263036588,"remaining_time":1.164421469},
{"learn":[0.2309997152],"iteration":737,"passed_time":3.266942698,"remaining_time":1.159808925},
{"learn":[0.2309147598],"iteration":738,"passed_time":3.271178765,"remaining_time":1.155314828},
{"learn":[0.2307892707],"iteration":739,"passed_time":3.275454393,"remaining_time":1.150835327},
{"learn":[0.2307073582],"iteration":740,"passed_time":3.279332327,"remaining_time":1.146217372},
{"learn":[0.2306180853],"iteration":741,"passed_time":3.283262753,"remaining_time":1.141619663},
{"learn":[0.2305263159],"iteration":742,"passed_time":3.287656585,"remaining_time":1.137184041},
{"learn":[0.2304590577],"iteration":743,"passed_time":3.291669448,"remaining_time":1.132617445},
{"learn":[0.2302985816],"iteration":744,"passed_time":3.295536618,"remaining_time":1.128002467},
{"learn":[0.2301765376],"iteration":745,"passed_time":3.299461354,"remaining_time":1.123409094},
{"learn":[0.2301191841],"iteration":746,"passed_time":3.304563495,"remaining_time":1.119216284},
{"learn":[0.2300708468],"iteration":747,"passed_time":3.310525891,"remaining_time":1.115310862},
{"learn":[0.229965064],"iteration":748,"passed_time":3.314649999,"remaining_time":1.110783912},
{"learn":[0.2298972042],"iteration":749,"passed_time":3.318514698,"remaining_time":1.106171566},
{"learn":[0.2297678072],"iteration":750,"passed_time":3.322767665,"remaining_time":1.101689945},
{"learn":[0.2297197278],"iteration":751,"passed_time":3.326785344,"remaining_time":1.097131337},
{"learn":[0.2296534111],"iteration":752,"passed_time":3.330732608,"remaining_time":1.092551068},
{"learn":[0.2295653756],"iteration":753,"passed_time":3.335818319,"remaining_time":1.088343908},
{"learn":[0.2294289612],"iteration":754,"passed_time":3.339687534,"remaining_time":1.083739663},
{"learn":[0.2293300408],"iteration":755,"passed_time":3.343659949,"remaining_time":1.079170671},
{"learn":[0.2292209425],"iteration":756,"passed_time":3.34767783,"remaining_time":1.07461785},
{"learn":[0.2291426724],"iteration":757,"passed_time":3.352429034,"remaining_time":1.070300562},
{"learn":[0.2290450745],"iteration":758,"passed_time":3.356388004,"remaining_time":1.065730578},
{"learn":[0.2289812821],"iteration":759,"passed_time":3.360764593,"remaining_time":1.061294082},
{"learn":[0.2288732263],"iteration":760,"passed_time":3.364741906,"remaining_time":1.056732346},
{"learn":[0.2287210933],"iteration":761,"passed_time":3.369541833,"remaining_time":1.052429076},
{"learn":[0.2286428885],"iteration":762,"passed_time":3.373582359,"remaining_time":1.047888623},
{"learn":[0.2285547538],"iteration":763,"passed_time":3.377399319,"remaining_time":1.043280418},
{"learn":[0.2284024198],"iteration":764,"passed_time":3.381273759,"remaining_time":1.038691939},
{"learn":[0.2283007926],"iteration":765,"passed_time":3.386276576,"remaining_time":1.034450025},
{"learn":[0.2282045553],"iteration":766,"passed_time":3.390133548,"remaining_time":1.02985804},
{"learn":[0.2281167581],"iteration":767,"passed_time":3.395468338,"remaining_time":1.025714394},
{"learn":[0.227980026],"iteration":768,"passed_time":3.399901799,"remaining_time":1.021296899},
{"learn":[0.2278796906],"iteration":769,"passed_time":3.404647911,"remaining_time":1.016972753},
{"learn":[0.2277842495],"iteration":770,"passed_time":3.409833578,"remaining_time":1.012778067},
{"learn":[0.227684954],"iteration":771,"passed_time":3.413812635,"remaining_time":1.008224457},
{"learn":[0.2275995837],"iteration":772,"passed_time":3.419537267,"remaining_time":1.004184941},
{"learn":[0.2275144194],"iteration":773,"passed_time":3.423491484,"remaining_time":0.9996241283},
{"learn":[0.2274623963],"iteration":774,"passed_time":3.427566329,"remaining_time":0.9950999019},
{"learn":[0.2273725461],"iteration":775,"passed_time":3.432686606,"remaining_time":0.990878608},
{"learn":[0.2273270695],"iteration":776,"passed_time":3.436596939,"remaining_time":0.9863077445},
{"learn":[0.2272149345],"iteration":777,"passed_time":3.440469751,"remaining_time":0.9817278723},
{"learn":[0.2271302771],"iteration":778,"passed_time":3.444256981,"remaining_time":0.9771255364},
{"learn":[0.2270698176],"iteration":779,"passed_time":3.449139656,"remaining_time":0.972834262},
{"learn":[0.2269873472],"iteration":780,"passed_time":3.453125687,"remaining_time":0.9682900454},
{"learn":[0.226869155],"iteration":781,"passed_time":3.456936724,"remaining_time":0.9636984728},
{"learn":[0.2268265981],"iteration":782,"passed_time":3.460878615,"remaining_time":0.959145159},
{"learn":[0.2266957637],"iteration":783,"passed_time":3.465803591,"remaining_time":0.9548642548},
{"learn":[0.2265952405],"iteration":784,"passed_time":3.469948313,"remaining_time":0.9503680093},
{"learn":[0.2264933589],"iteration":785,"passed_time":3.47373412,"remaining_time":0.9457749384},
{"learn":[0.2263703086],"iteration":786,"passed_time":3.477626173,"remaining_time":0.9412126745},
{"learn":[0.2262899539],"iteration":787,"passed_time":3.482357931,"remaining_time":0.9368780219},
{"learn":[0.2262136127],"iteration":788,"passed_time":3.486183769,"remaining_time":0.9323000953},
{"learn":[0.2261497808],"iteration":789,"passed_time":3.490074156,"remaining_time":0.9277412313},
{"learn":[0.226053007],"iteration":790,"passed_time":3.493819003,"remaining_time":0.9231456026},
{"learn":[0.2259867709],"iteration":791,"passed_time":3.498716361,"remaining_time":0.918854802},
{"learn":[0.2258556519],"iteration":792,"passed_time":3.502478194,"remaining_time":0.9142660606},
{"learn":[0.2257855195],"iteration":793,"passed_time":3.50617774,"remaining_time":0.9096632424},
{"learn":[0.2257109371],"iteration":794,"passed_time":3.510195282,"remaining_time":0.9051446954},
{"learn":[0.2256433578],"iteration":795,"passed_time":3.515453429,"remaining_time":0.9009453513},
{"learn":[0.2255551967],"iteration":796,"passed_time":3.520046839,"remaining_time":0.896574038},
{"learn":[0.2254573563],"iteration":797,"passed_time":3.523821667,"remaining_time":0.8919949583},
{"learn":[0.2253602788],"iteration":798,"passed_time":3.528359704,"remaining_time":0.8876098879},
{"learn":[0.2252335617],"iteration":799,"passed_time":3.532317925,"remaining_time":0.8830794813},
{"learn":[0.2251245717],"iteration":800,"passed_time":3.536183868,"remaining_time":0.8785275778},
{"learn":[0.2250476668],"iteration":801,"passed_time":3.540301982,"remaining_time":0.8740396414},
{"learn":[0.2249778491],"iteration":802,"passed_time":3.54508297,"remaining_time":0.8697152491},
{"learn":[0.2249051356],"iteration":803,"passed_time":3.548875679,"remaining_time":0.8651487974},
{"learn":[0.224805126],"iteration":804,"passed_time":3.552689954,"remaining_time":0.8605894919},
{"learn":[0.2247335281],"iteration":805,"passed_time":3.556664944,"remaining_time":0.8560707184},
{"learn":[0.2246615236],"iteration":806,"passed_time":3.561497591,"remaining_time":0.8517584079},
{"learn":[0.2245864034],"iteration":807,"passed_time":3.565404224,"remaining_time":0.8472247662},
{"learn":[0.2244615868],"iteration":808,"passed_time":3.569136012,"remaining_time":0.8426513947},
{"learn":[0.2244243964],"iteration":809,"passed_time":3.572899113,"remaining_time":0.8380874463},
{"learn":[0.2243395423],"iteration":810,"passed_time":3.578365909,"remaining_time":0.8339225114},
{"learn":[0.2242065256],"iteration":811,"passed_time":3.582325101,"remaining_time":0.8294053188},
{"learn":[0.2241190734],"iteration":812,"passed_time":3.58627381,"remaining_time":0.8248870878},
{"learn":[0.2240691976],"iteration":813,"passed_time":3.590006311,"remaining_time":0.8203208525},
{"learn":[0.2239649475],"iteration":814,"passed_time":3.595100461,"remaining_time":0.8160657487},
{"learn":[0.2238475015],"iteration":815,"passed_time":3.598923246,"remaining_time":0.8115219083},
{"learn":[0.2237290452],"iteration":816,"passed_time":3.602652538,"remaining_time":0.8069588916},
{"learn":[0.2236251237],"iteration":817,"passed_time":3.606499247,"remaining_time":0.8024240378},
{"learn":[0.2235108014],"iteration":818,"passed_time":3.612165606,"remaining_time":0.7982930094},
{"learn":[0.2234233501],"iteration":819,"passed_time":3.617689127,"remaining_time":0.7941268816},
{"learn":[0.2233317725],"iteration":820,"passed_time":3.621757398,"remaining_time":0.7896401635},
{"learn":[0.2232798313],"iteration":821,"passed_time":3.627645731,"remaining_time":0.7855485889},
{"learn":[0.2232248589],"iteration":822,"passed_time":3.631603025,"remaining_time":0.7810373455},
{"learn":[0.2231642995],"iteration":823,"passed_time":3.635731064,"remaining_time":0.7765639166},
{"learn":[0.2230415246],"iteration":824,"passed_time":3.64091883,"remaining_time":0.7723161154},
{"learn":[0.2229260583],"iteration":825,"passed_time":3.645681838,"remaining_time":0.7679765615},
{"learn":[0.222832867],"iteration":826,"passed_time":3.649799414,"remaining_time":0.7635009657},
{"learn":[0.222749731],"iteration":827,"passed_time":3.653712969,"remaining_time":0.7589838535},
{"learn":[0.2226813544],"iteration":828,"passed_time":3.658700775,"remaining_time":0.754689786},
{"learn":[0.222610076],"iteration":829,"passed_time":3.662442716,"remaining_time":0.7501388696},
{"learn":[0.2225244129],"iteration":830,"passed_time":3.666255441,"remaining_time":0.7456042954},
{"learn":[0.2224170632],"iteration":831,"passed_time":3.669976279,"remaining_time":0.7410529025},
{"learn":[0.2223329124],"iteration":832,"passed_time":3.675149331,"remaining_time":0.7367946438},
{"learn":[0.2222492566],"iteration":833,"passed_time":3.678946204,"remaining_time":0.7322602756},
{"learn":[0.2221450524],"iteration":834,"passed_time":3.682979597,"remaining_time":0.7277744114},
{"learn":[0.2220644473],"iteration":835,"passed_time":3.686730732,"remaining_time":0.7232342584},
{"learn":[0.222000936],"iteration":836,"passed_time":3.691710006,"remaining_time":0.7189351624},
{"learn":[0.2218877157],"iteration":837,"passed_time":3.695572887,"remaining_time":0.714418625},
{"learn":[0.2218120848],"iteration":838,"passed_time":3.699427038,"remaining_time":0.7099019703},
{"learn":[0.2217229494],"iteration":839,"passed_time":3.70333407,"remaining_time":0.7053969657},
{"learn":[0.2215719476],"iteration":840,"passed_time":3.708484495,"remaining_time":0.7011284598},
{"learn":[0.2215090763],"iteration":841,"passed_time":3.712642513,"remaining_time":0.6966716354},
{"learn":[0.221423369],"iteration":842,"passed_time":3.716427553,"remaining_time":0.6921460568},
{"learn":[0.2213476924],"iteration":843,"passed_time":3.721102645,"remaining_time":0.6877867447},
{"learn":[0.2212647186],"iteration":844,"passed_time":3.724950837,"remaining_time":0.6832750056},
{"learn":[0.2211421721],"iteration":845,"passed_time":3.728880392,"remaining_time":0.6787796457},
{"learn":[0.2210645283],"iteration":846,"passed_time":3.732701842,"remaining_time":0.6742660942},
{"learn":[0.2209962646],"iteration":847,"passed_time":3.737348543,"remaining_time":0.6699020972},
{"learn":[0.2208493568],"iteration":848,"passed_time":3.741237492,"remaining_time":0.6654026634},
{"learn":[0.2207871534],"iteration":849,"passed_time":3.744984168,"remaining_time":0.660879559},
{"learn":[0.2206720536],"iteration":850,"passed_time":3.74914078,"remaining_time":0.6564300542},
{"learn":[0.2206023838],"iteration":851,"passed_time":3.753848304,"remaining_time":0.6520769354},
{"learn":[0.2204817524],"iteration":852,"passed_time":3.757698405,"remaining_time":0.6475752233},
{"learn":[0.2204115279],"iteration":853,"passed_time":3.761506364,"remaining_time":0.6430678328},
{"learn":[0.220341946],"iteration":854,"passed_time":3.765319136,"remaining_time":0.6385628945},
{"learn":[0.2202520271],"iteration":855,"passed_time":3.7700922,"remaining_time":0.6342211177},
{"learn":[0.2201860312],"iteration":856,"passed_time":3.773856658,"remaining_time":0.6297100374},
{"learn":[0.220078472],"iteration":857,"passed_time":3.777757199,"remaining_time":0.6252232194},
{"learn":[0.2199624593],"iteration":858,"passed_time":3.781531609,"remaining_time":0.6207170627},
{"learn":[0.2198999937],"iteration":859,"passed_time":3.786398586,"remaining_time":0.6163904674},
{"learn":[0.2197992786],"iteration":860,"passed_time":3.790443782,"remaining_time":0.6119299485},
{"learn":[0.2196813333],"iteration":861,"passed_time":3.794293643,"remaining_time":0.6074391216},
{"learn":[0.2196010401],"iteration":862,"passed_time":3.798202328,"remaining_time":0.6029591181},
{"learn":[0.2195371315],"iteration":863,"passed_time":3.804355058,"remaining_time":0.5988336665},
{"learn":[0.2194784976],"iteration":864,"passed_time":3.808575189,"remaining_time":0.5944019081},
{"learn":[0.219371772],"iteration":865,"passed_time":3.812402895,"remaining_time":0.5899099168},
{"learn":[0.219284058],"iteration":866,"passed_time":3.817086381,"remaining_time":0.5855507367},
{"learn":[0.219226593],"iteration":867,"passed_time":3.821028061,"remaining_time":0.581078},
{"learn":[0.2191026438],"iteration":868,"passed_time":3.825355443,"remaining_time":0.5766646296},
{"learn":[0.219000281],"iteration":869,"passed_time":3.8302876,"remaining_time":0.5723418253},
{"learn":[0.2188998348],"iteration":870,"passed_time":3.836254822,"remaining_time":0.5681709209},
{"learn":[0.2187640094],"iteration":871,"passed_time":3.840211892,"remaining_time":0.5637008281},
{"learn":[0.2186823052],"iteration":872,"passed_time":3.844100198,"remaining_time":0.5592219074},
{"learn":[0.2186214426],"iteration":873,"passed_time":3.850382971,"remaining_time":0.5550895359},
{"learn":[0.218563811],"iteration":874,"passed_time":3.854626155,"remaining_time":0.5506608792},
{"learn":[0.2185122591],"iteration":875,"passed_time":3.858444579,"remaining_time":0.5461725203},
{"learn":[0.21845097],"iteration":876,"passed_time":3.862316727,"remaining_time":0.541693224},
{"learn":[0.2183288282],"iteration":877,"passed_time":3.867457389,"remaining_time":0.5373915734},
{"learn":[0.2182334157],"iteration":878,"passed_time":3.871416584,"remaining_time":0.5329253773},
{"learn":[0.2181668914],"iteration":879,"passed_time":3.875428452,"remaining_time":0.5284675161},
{"learn":[0.2180883146],"iteration":880,"passed_time":3.879166085,"remaining_time":0.5239736255},
{"learn":[0.2180009145],"iteration":881,"passed_time":3.884161513,"remaining_time":0.5196497262},
{"learn":[0.2179136741],"iteration":882,"passed_time":3.888021012,"remaining_time":0.5151737921},
{"learn":[0.217825387],"iteration":883,"passed_time":3.891857142,"remaining_time":0.5106961861},
{"learn":[0.2177758547],"iteration":884,"passed_time":3.895774606,"remaining_time":0.5062305985},
{"learn":[0.2177108569],"iteration":885,"passed_time":3.899638668,"remaining_time":0.5017593771},
{"learn":[0.2176577643],"iteration":886,"passed_time":3.903635353,"remaining_time":0.4973064204},
{"learn":[0.2175397296],"iteration":887,"passed_time":3.907534089,"remaining_time":0.4928421373},
{"learn":[0.2174800506],"iteration":888,"passed_time":3.911905354,"remaining_time":0.4884381263},
{"learn":[0.2173849917],"iteration":889,"passed_time":3.916937887,"remaining_time":0.4841159187},
{"learn":[0.2172540141],"iteration":890,"passed_time":3.920984013,"remaining_time":0.4796714449},
{"learn":[0.2171901604],"iteration":891,"passed_time":3.924853851,"remaining_time":0.4752065201},
{"learn":[0.217123726],"iteration":892,"passed_time":3.929754932,"remaining_time":0.4708664925},
{"learn":[0.2170309762],"iteration":893,"passed_time":3.93371419,"remaining_time":0.4664135393},
{"learn":[0.2169485999],"iteration":894,"passed_time":3.937509761,"remaining_time":0.4619424859},
{"learn":[0.2168631663],"iteration":895,"passed_time":3.941513827,"remaining_time":0.4574971406},
{"learn":[0.216764689],"iteration":896,"passed_time":3.946183835,"remaining_time":0.4531292475},
{"learn":[0.2167006316],"iteration":897,"passed_time":3.950206493,"remaining_time":0.4486871517},
{"learn":[0.216637635],"iteration":898,"passed_time":3.954211875,"remaining_time":0.4442440482},
{"learn":[0.2165832528],"iteration":899,"passed_time":3.958075416,"remaining_time":0.4397861574},
{"learn":[0.2164888444],"iteration":900,"passed_time":3.962911811,"remaining_time":0.4354364809},
{"learn":[0.2164301504],"iteration":901,"passed_time":3.966786606,"remaining_time":0.4309812499},
{"learn":[0.216316046],"iteration":902,"passed_time":3.970781618,"remaining_time":0.4265402181},
{"learn":[0.2162122362],"iteration":903,"passed_time":3.974617638,"remaining_time":0.422083289},
{"learn":[0.2161215099],"iteration":904,"passed_time":3.979532763,"remaining_time":0.4177410082},
{"learn":[0.2160492489],"iteration":905,"passed_time":3.983253275,"remaining_time":0.4132735186},
{"learn":[0.2159601637],"iteration":906,"passed_time":3.987060877,"remaining_time":0.408816606},
{"learn":[0.2158726252],"iteration":907,"passed_time":3.990938241,"remaining_time":0.4043681918},
{"learn":[0.2158036127],"iteration":908,"passed_time":3.99494985,"remaining_time":0.3999344735},
{"learn":[0.215691571],"iteration":909,"passed_time":3.999311766,"remaining_time":0.3955363285},
{"learn":[0.2155693279],"iteration":910,"passed_time":4.003393349,"remaining_time":0.391110876},
{"learn":[0.2154533554],"iteration":911,"passed_time":4.008041129,"remaining_time":0.3867408107},
{"learn":[0.2153387236],"iteration":912,"passed_time":4.013646985,"remaining_time":0.3824614323},
{"learn":[0.2152630839],"iteration":913,"passed_time":4.018593003,"remaining_time":0.3781170659},
{"learn":[0.2151162127],"iteration":914,"passed_time":4.023338368,"remaining_time":0.3737527446},
{"learn":[0.2150663248],"iteration":915,"passed_time":4.028167391,"remaining_time":0.3693952629},
{"learn":[0.2149967661],"iteration":916,"passed_time":4.032000901,"remaining_time":0.3649466465},
{"learn":[0.2148990664],"iteration":917,"passed_time":4.036820045,"remaining_time":0.3605874115},
{"learn":[0.2148104808],"iteration":918,"passed_time":4.043060039,"remaining_time":0.3563524082},
{"learn":[0.2146882149],"iteration":919,"passed_time":4.046920657,"remaining_time":0.3519061441},
{"learn":[0.214585574],"iteration":920,"passed_time":4.050782313,"remaining_time":0.3474612407},
{"learn":[0.2144901739],"iteration":921,"passed_time":4.055809984,"remaining_time":0.343116246},
{"learn":[0.2143894293],"iteration":922,"passed_time":4.059518772,"remaining_time":0.3386597459},
{"learn":[0.2142932629],"iteration":923,"passed_time":4.063368622,"remaining_time":0.3342164668},
{"learn":[0.2142345747],"iteration":924,"passed_time":4.067238144,"remaining_time":0.3297760657},
{"learn":[0.2141752283],"iteration":925,"passed_time":4.071616651,"remaining_time":0.3253775725},
{"learn":[0.2141097082],"iteration":926,"passed_time":4.076054127,"remaining_time":0.3209837662},
{"learn":[0.2140650977],"iteration":927,"passed_time":4.079818723,"remaining_time":0.3165376595},
{"learn":[0.2139765864],"iteration":928,"passed_time":4.083646087,"remaining_time":0.3120978172},
{"learn":[0.2138778086],"iteration":929,"passed_time":4.088395603,"remaining_time":0.3077287013},
{"learn":[0.2137953592],"iteration":930,"passed_time":4.092333956,"remaining_time":0.3032986498},
{"learn":[0.2136788679],"iteration":931,"passed_time":4.096227748,"remaining_time":0.2988664022},
{"learn":[0.2135855671],"iteration":932,"passed_time":4.099984572,"remaining_time":0.294425473},
{"learn":[0.2134778532],"iteration":933,"passed_time":4.104794321,"remaining_time":0.2900604124},
{"learn":[0.2133735646],"iteration":934,"passed_time":4.109751746,"remaining_time":0.2857046668},
{"learn":[0.2133159923],"iteration":935,"passed_time":4.113539687,"remaining_time":0.2812676709},
{"learn":[0.2132149183],"iteration":936,"passed_time":4.117363409,"remaining_time":0.2768344662},
{"learn":[0.2131059437],"iteration":937,"passed_time":4.12213703,"remaining_time":0.2724653474},
{"learn":[0.212970964],"iteration":938,"passed_time":4.125981405,"remaining_time":0.2680350008},
{"learn":[0.2128409451],"iteration":939,"passed_time":4.130034242,"remaining_time":0.2636192069},
{"learn":[0.2127886476],"iteration":940,"passed_time":4.133864175,"remaining_time":0.2591902086},
{"learn":[0.2127246346],"iteration":941,"passed_time":4.138493767,"remaining_time":0.2548117181},
{"learn":[0.2126226357],"iteration":942,"passed_time":4.142367803,"remaining_time":0.2503870252},
{"learn":[0.2125574123],"iteration":943,"passed_time":4.146067057,"remaining_time":0.2459531305},
{"learn":[0.212485951],"iteration":944,"passed_time":4.149910026,"remaining_time":0.2415291549},
{"learn":[0.212383085],"iteration":945,"passed_time":4.154814938,"remaining_time":0.2371670261},
{"learn":[0.2123188208],"iteration":946,"passed_time":4.15867083,"remaining_time":0.2327450412},
{"learn":[0.2122454661],"iteration":947,"passed_time":4.16258147,"remaining_time":0.2283272536},
{"learn":[0.2121713442],"iteration":948,"passed_time":4.166422904,"remaining_time":0.2239068157},
{"learn":[0.212103011],"iteration":949,"passed_time":4.171731005,"remaining_time":0.2195647897},
{"learn":[0.2120473284],"iteration":950,"passed_time":4.175497893,"remaining_time":0.2151413215},
{"learn":[0.2119452734],"iteration":951,"passed_time":4.179240214,"remaining_time":0.210717994},
{"learn":[0.211820163],"iteration":952,"passed_time":4.184138156,"remaining_time":0.2063530885},
{"learn":[0.2117274382],"iteration":953,"passed_time":4.188126294,"remaining_time":0.2019431966},
{"learn":[0.2116382288],"iteration":954,"passed_time":4.192005366,"remaining_time":0.1975290487},
{"learn":[0.2115300073],"iteration":955,"passed_time":4.195899704,"remaining_time":0.1931167228},
{"learn":[0.2114120541],"iteration":956,"passed_time":4.20033636,"remaining_time":0.1887298469},
{"learn":[0.2113514345],"iteration":957,"passed_time":4.20569522,"remaining_time":0.1843832978},
{"learn":[0.2112506614],"iteration":958,"passed_time":4.209674895,"remaining_time":0.1799756733},
{"learn":[0.2111788788],"iteration":959,"passed_time":4.213497256,"remaining_time":0.1755623857},
{"learn":[0.2110570226],"iteration":960,"passed_time":4.218411452,"remaining_time":0.1711946375},
{"learn":[0.2109886876],"iteration":961,"passed_time":4.222328299,"remaining_time":0.1667863569},
{"learn":[0.2109134903],"iteration":962,"passed_time":4.226288352,"remaining_time":0.162380757},
{"learn":[0.2108160138],"iteration":963,"passed_time":4.23257599,"remaining_time":0.1580630038},
{"learn":[0.2107189761],"iteration":964,"passed_time":4.237718885,"remaining_time":0.1536996487},
{"learn":[0.2106464984],"iteration":965,"passed_time":4.241585067,"remaining_time":0.1492897436},
{"learn":[0.2105427607],"iteration":966,"passed_time":4.245499959,"remaining_time":0.1448826253},
{"learn":[0.2104708184],"iteration":967,"passed_time":4.250808474,"remaining_time":0.1405225942},
{"learn":[0.2103856161],"iteration":968,"passed_time":4.254658423,"remaining_time":0.1361139434},
{"learn":[0.2103016302],"iteration":969,"passed_time":4.25862013,"remaining_time":0.1317099009},
{"learn":[0.2102508219],"iteration":970,"passed_time":4.264130834,"remaining_time":0.1273530321},
{"learn":[0.2101868269],"iteration":971,"passed_time":4.268846332,"remaining_time":0.122970882},
{"learn":[0.2100746668],"iteration":972,"passed_time":4.272837575,"remaining_time":0.1185679491},
{"learn":[0.2100285118],"iteration":973,"passed_time":4.276774889,"remaining_time":0.1141644221},
{"learn":[0.2099512972],"iteration":974,"passed_time":4.281784111,"remaining_time":0.1097893362},
{"learn":[0.2098925556],"iteration":975,"passed_time":4.285866728,"remaining_time":0.1053901654},
{"learn":[0.2098112366],"iteration":976,"passed_time":4.289691487,"remaining_time":0.1009855724},
{"learn":[0.209764777],"iteration":977,"passed_time":4.293499446,"remaining_time":0.09658178713},
{"learn":[0.2096952613],"iteration":978,"passed_time":4.298798039,"remaining_time":0.09221119389},
{"learn":[0.2096334795],"iteration":979,"passed_time":4.303218092,"remaining_time":0.0878207774},
{"learn":[0.209554473],"iteration":980,"passed_time":4.307115961,"remaining_time":0.0834201868},
{"learn":[0.2094454406],"iteration":981,"passed_time":4.310861467,"remaining_time":0.0790178273},
{"learn":[0.2093408881],"iteration":982,"passed_time":4.315498811,"remaining_time":0.07463222765},
{"learn":[0.2092425061],"iteration":983,"passed_time":4.31982755,"remaining_time":0.07024109837},
{"learn":[0.2091810144],"iteration":984,"passed_time":4.324009509,"remaining_time":0.06584786054},
{"learn":[0.2091074411],"iteration":985,"passed_time":4.328572223,"remaining_time":0.06146045752},
{"learn":[0.2090296339],"iteration":986,"passed_time":4.332564133,"remaining_time":0.05706518108},
{"learn":[0.2089748781],"iteration":987,"passed_time":4.33638188,"remaining_time":0.05266860583},
{"learn":[0.2089148732],"iteration":988,"passed_time":4.340132933,"remaining_time":0.04827245931},
{"learn":[0.2088749666],"iteration":989,"passed_time":4.344551379,"remaining_time":0.04388435736},
{"learn":[0.208810689],"iteration":990,"passed_time":4.348375793,"remaining_time":0.03949079933},
{"learn":[0.2087310861],"iteration":991,"passed_time":4.352625036,"remaining_time":0.0351018148},
{"learn":[0.2086986389],"iteration":992,"passed_time":4.356504106,"remaining_time":0.03071050226},
{"learn":[0.2085935146],"iteration":993,"passed_time":4.361035106,"remaining_time":0.02632415557},
{"learn":[0.2085233916],"iteration":994,"passed_time":4.364880789,"remaining_time":0.02193407431},
{"learn":[0.2084471651],"iteration":995,"passed_time":4.368650748,"remaining_time":0.01754478212},
{"learn":[0.2083720786],"iteration":996,"passed_time":4.37302954,"remaining_time":0.01315856431},
{"learn":[0.2083201129],"iteration":997,"passed_time":4.377844327,"remaining_time":0.008773235124},
{"learn":[0.2082304922],"iteration":998,"passed_time":4.381715108,"remaining_time":0.004386101209},
{"learn":[0.2081055612],"iteration":999,"passed_time":4.385557905,"remaining_time":0}
]}